<?xml version="1.0" encoding="ISO-8859-1"?>
<Vehicle menyoo_ver="0.99987681b">
	<ModelHash>0xdff0594c</ModelHash>
	<InitialHandle>612443</InitialHandle>
	<VehicleProperties>
		<Colours>
			<Primary>46</Primary>
			<Secondary>0</Secondary>
			<Pearl>46</Pearl>
			<Rim>156</Rim>
			<Mod1_a>32767</Mod1_a>
			<Mod1_b>32767</Mod1_b>
			<Mod1_c>2568192</Mod1_c>
			<Mod2_a>722465408</Mod2_a>
			<Mod2_b>32767</Mod2_b>
			<IsPrimaryColourCustom>false</IsPrimaryColourCustom>
			<IsSecondaryColourCustom>false</IsSecondaryColourCustom>
			<tyreSmoke_R>255</tyreSmoke_R>
			<tyreSmoke_G>255</tyreSmoke_G>
			<tyreSmoke_B>255</tyreSmoke_B>
			<LrInterior>0</LrInterior>
			<LrDashboard>0</LrDashboard>
		</Colours>
		<Livery>-1</Livery>
		<NumberPlateText>24RHE196</NumberPlateText>
		<NumberPlateIndex>3</NumberPlateIndex>
		<WheelType>0</WheelType>
		<WheelsInvisible>false</WheelsInvisible>
		<EngineSoundName></EngineSoundName>
		<WindowTint>-1</WindowTint>
		<BulletProofTyres>true</BulletProofTyres>
		<DirtLevel>0.176147595</DirtLevel>
		<PaintFade>0.298039228</PaintFade>
		<RoofState>0</RoofState>
		<SirenActive>false</SirenActive>
		<EngineOn>true</EngineOn>
		<EngineHealth>1000</EngineHealth>
		<LightsOn>false</LightsOn>
		<IsRadioLoud>0</IsRadioLoud>
		<LockStatus>1</LockStatus>
		<Neons>
			<Left>false</Left>
			<Right>false</Right>
			<Front>false</Front>
			<Back>false</Back>
			<R>255</R>
			<G>0</G>
			<B>255</B>
		</Neons>
		<ModExtras>
			<_2>false</_2>
		</ModExtras>
		<Mods>
			<_0>-1,0</_0>
			<_1>-1,0</_1>
			<_2>-1,0</_2>
			<_3>-1,0</_3>
			<_4>-1,0</_4>
			<_5>-1,0</_5>
			<_6>-1,0</_6>
			<_7>-1,0</_7>
			<_8>-1,0</_8>
			<_9>-1,0</_9>
			<_10>-1,0</_10>
			<_11>-1,0</_11>
			<_12>-1,0</_12>
			<_13>-1,0</_13>
			<_14>-1,0</_14>
			<_15>-1,0</_15>
			<_16>-1,0</_16>
			<_17>false</_17>
			<_18>false</_18>
			<_19>false</_19>
			<_20>false</_20>
			<_21>false</_21>
			<_22>false</_22>
			<_23>-1,0</_23>
			<_24>-1,0</_24>
			<_25>-1,0</_25>
			<_26>-1,0</_26>
			<_27>-1,0</_27>
			<_28>-1,0</_28>
			<_29>-1,0</_29>
			<_30>-1,0</_30>
			<_31>-1,0</_31>
			<_32>-1,0</_32>
			<_33>-1,0</_33>
			<_34>-1,0</_34>
			<_35>-1,0</_35>
			<_36>-1,0</_36>
			<_37>-1,0</_37>
			<_38>-1,0</_38>
			<_39>-1,0</_39>
			<_40>-1,0</_40>
			<_41>-1,0</_41>
			<_42>-1,0</_42>
			<_43>-1,0</_43>
			<_44>-1,0</_44>
			<_45>-1,0</_45>
			<_46>-1,0</_46>
			<_47>-1,0</_47>
			<_48>-1,0</_48>
		</Mods>
		<DoorsOpen>
			<BackLeftDoor>false</BackLeftDoor>
			<BackRightDoor>false</BackRightDoor>
			<FrontLeftDoor>false</FrontLeftDoor>
			<FrontRightDoor>false</FrontRightDoor>
			<Hood>false</Hood>
			<Trunk>false</Trunk>
			<Trunk2>false</Trunk2>
		</DoorsOpen>
		<DoorsBroken>
			<BackLeftDoor>false</BackLeftDoor>
			<BackRightDoor>false</BackRightDoor>
			<FrontLeftDoor>false</FrontLeftDoor>
			<FrontRightDoor>false</FrontRightDoor>
			<Hood>false</Hood>
			<Trunk>false</Trunk>
			<Trunk2>false</Trunk2>
		</DoorsBroken>
		<TyresBursted>
			<FrontLeft>false</FrontLeft>
			<FrontRight>false</FrontRight>
			<_2>false</_2>
			<_3>false</_3>
			<BackLeft>false</BackLeft>
			<BackRight>false</BackRight>
			<_6>false</_6>
			<_7>false</_7>
			<_8>false</_8>
		</TyresBursted>
	</VehicleProperties>
	<OpacityLevel>0</OpacityLevel>
	<LodDistance>16960</LodDistance>
	<IsVisible>true</IsVisible>
	<IsDriverVisible>true</IsDriverVisible>
	<MaxHealth>1000</MaxHealth>
	<Health>1000</Health>
	<HasGravity>true</HasGravity>
	<IsOnFire>false</IsOnFire>
	<IsInvincible>true</IsInvincible>
	<IsBulletProof>true</IsBulletProof>
	<IsExplosionProof>true</IsExplosionProof>
	<IsFireProof>false</IsFireProof>
	<IsMeleeProof>true</IsMeleeProof>
	<IsOnlyDamagedByPlayer>false</IsOnlyDamagedByPlayer>
	<SpoonerAttachments SetAttachmentsPersistentAndAddToSpoonerDatabase="true" StartTaskSequencesOnLoad="true">
		<Attachment>
			<ModelHash>0x0fe7673c</ModelHash>
			<Type>3</Type>
			<Dynamic>false</Dynamic>
			<FrozenPos>true</FrozenPos>
			<HashName>prop_couch_sm2_07</HashName>
			<InitialHandle>247899</InitialHandle>
			<ObjectProperties>
				<TextureVariation>0</TextureVariation>
			</ObjectProperties>
			<OpacityLevel>255</OpacityLevel>
			<LodDistance>16960</LodDistance>
			<IsVisible>true</IsVisible>
			<MaxHealth>1000</MaxHealth>
			<Health>1000</Health>
			<HasGravity>true</HasGravity>
			<IsOnFire>false</IsOnFire>
			<IsInvincible>true</IsInvincible>
			<IsBulletProof>false</IsBulletProof>
			<IsCollisionProof>true</IsCollisionProof>
			<IsExplosionProof>true</IsExplosionProof>
			<IsFireProof>true</IsFireProof>
			<IsMeleeProof>true</IsMeleeProof>
			<IsOnlyDamagedByPlayer>false</IsOnlyDamagedByPlayer>
			<PositionRotation>
				<X>-1287.02478</X>
				<Y>-2971.78931</Y>
				<Z>13.1387014</Z>
				<Pitch>0.0205666218</Pitch>
				<Roll>0.000792502135</Roll>
				<Yaw>-120.856979</Yaw>
			</PositionRotation>
			<Attachment isAttached="true">
				<AttachedTo>612443</AttachedTo>
				<BoneIndex>0</BoneIndex>
				<X>0</X>
				<Y>-0.329999983</Y>
				<Z>-0.199999988</Z>
				<Pitch>0</Pitch>
				<Roll>0</Roll>
				<Yaw>-179.999985</Yaw>
			</Attachment>
		</Attachment>
		<Attachment>
			<ModelHash>0x1e3763e5</ModelHash>
			<Type>3</Type>
			<Dynamic>false</Dynamic>
			<FrozenPos>true</FrozenPos>
			<HashName>prop_surf_board_ldn_01</HashName>
			<InitialHandle>672859</InitialHandle>
			<ObjectProperties>
				<TextureVariation>0</TextureVariation>
			</ObjectProperties>
			<OpacityLevel>255</OpacityLevel>
			<LodDistance>16960</LodDistance>
			<IsVisible>true</IsVisible>
			<MaxHealth>1000</MaxHealth>
			<Health>1000</Health>
			<HasGravity>true</HasGravity>
			<IsOnFire>false</IsOnFire>
			<IsInvincible>true</IsInvincible>
			<IsBulletProof>false</IsBulletProof>
			<IsCollisionProof>true</IsCollisionProof>
			<IsExplosionProof>true</IsExplosionProof>
			<IsFireProof>true</IsFireProof>
			<IsMeleeProof>true</IsMeleeProof>
			<IsOnlyDamagedByPlayer>false</IsOnlyDamagedByPlayer>
			<PositionRotation>
				<X>-1287.51318</X>
				<Y>-2971.96362</Y>
				<Z>13.0185776</Z>
				<Pitch>-90</Pitch>
				<Roll>-59.1429863</Roll>
				<Yaw>0</Yaw>
			</PositionRotation>
			<Attachment isAttached="true">
				<AttachedTo>612443</AttachedTo>
				<BoneIndex>0</BoneIndex>
				<X>-0.399999976</X>
				<Y>0</Y>
				<Z>-0.319999963</Z>
				<Pitch>-89.9999924</Pitch>
				<Roll>0</Roll>
				<Yaw>0</Yaw>
			</Attachment>
		</Attachment>
		<Attachment>
			<ModelHash>0x1e3763e5</ModelHash>
			<Type>3</Type>
			<Dynamic>false</Dynamic>
			<FrozenPos>true</FrozenPos>
			<HashName>prop_surf_board_ldn_01</HashName>
			<InitialHandle>417627</InitialHandle>
			<ObjectProperties>
				<TextureVariation>0</TextureVariation>
			</ObjectProperties>
			<OpacityLevel>255</OpacityLevel>
			<LodDistance>16960</LodDistance>
			<IsVisible>true</IsVisible>
			<MaxHealth>1000</MaxHealth>
			<Health>1000</Health>
			<HasGravity>true</HasGravity>
			<IsOnFire>false</IsOnFire>
			<IsInvincible>true</IsInvincible>
			<IsBulletProof>false</IsBulletProof>
			<IsCollisionProof>true</IsCollisionProof>
			<IsExplosionProof>true</IsExplosionProof>
			<IsFireProof>true</IsFireProof>
			<IsMeleeProof>true</IsMeleeProof>
			<IsOnlyDamagedByPlayer>false</IsOnlyDamagedByPlayer>
			<PositionRotation>
				<X>-1287.05994</X>
				<Y>-2971.30249</Y>
				<Z>13.0186062</Z>
				<Pitch>-89.3101578</Pitch>
				<Roll>-179.822479</Roll>
				<Yaw>-124.439499</Yaw>
			</PositionRotation>
			<Attachment isAttached="true">
				<AttachedTo>612443</AttachedTo>
				<BoneIndex>0</BoneIndex>
				<X>0.399999887</X>
				<Y>-0.049999997</Y>
				<Z>-0.319999963</Z>
				<Pitch>-90.6699982</Pitch>
				<Roll>0</Roll>
				<Yaw>-3.75999689</Yaw>
			</Attachment>
		</Attachment>
		<Attachment>
			<ModelHash>0x46a578b5</ModelHash>
			<Type>3</Type>
			<Dynamic>false</Dynamic>
			<FrozenPos>true</FrozenPos>
			<HashName>prop_ld_rope_t</HashName>
			<InitialHandle>699483</InitialHandle>
			<ObjectProperties>
				<TextureVariation>0</TextureVariation>
			</ObjectProperties>
			<OpacityLevel>255</OpacityLevel>
			<LodDistance>16960</LodDistance>
			<IsVisible>true</IsVisible>
			<MaxHealth>1000</MaxHealth>
			<Health>1000</Health>
			<HasGravity>true</HasGravity>
			<IsOnFire>false</IsOnFire>
			<IsInvincible>true</IsInvincible>
			<IsBulletProof>false</IsBulletProof>
			<IsCollisionProof>true</IsCollisionProof>
			<IsExplosionProof>true</IsExplosionProof>
			<IsFireProof>true</IsFireProof>
			<IsMeleeProof>true</IsMeleeProof>
			<IsOnlyDamagedByPlayer>false</IsOnlyDamagedByPlayer>
			<PositionRotation>
				<X>-1286.50195</X>
				<Y>-2971.63574</Y>
				<Z>12.9388399</Z>
				<Pitch>-57.5202789</Pitch>
				<Roll>-0.00147700869</Roll>
				<Yaw>59.1417427</Yaw>
			</PositionRotation>
			<Attachment isAttached="true">
				<AttachedTo>612443</AttachedTo>
				<BoneIndex>0</BoneIndex>
				<X>0.399999976</X>
				<Y>-0.699999928</Y>
				<Z>-0.399999976</Z>
				<Pitch>-57.4996948</Pitch>
				<Roll>0</Roll>
				<Yaw>0</Yaw>
			</Attachment>
		</Attachment>
		<Attachment>
			<ModelHash>0x46a578b5</ModelHash>
			<Type>3</Type>
			<Dynamic>false</Dynamic>
			<FrozenPos>true</FrozenPos>
			<HashName>prop_ld_rope_t</HashName>
			<InitialHandle>682075</InitialHandle>
			<ObjectProperties>
				<TextureVariation>0</TextureVariation>
			</ObjectProperties>
			<OpacityLevel>255</OpacityLevel>
			<LodDistance>16960</LodDistance>
			<IsVisible>true</IsVisible>
			<MaxHealth>1000</MaxHealth>
			<Health>1000</Health>
			<HasGravity>true</HasGravity>
			<IsOnFire>false</IsOnFire>
			<IsInvincible>true</IsInvincible>
			<IsBulletProof>false</IsBulletProof>
			<IsCollisionProof>true</IsCollisionProof>
			<IsExplosionProof>true</IsExplosionProof>
			<IsFireProof>true</IsFireProof>
			<IsMeleeProof>true</IsMeleeProof>
			<IsOnlyDamagedByPlayer>false</IsOnlyDamagedByPlayer>
			<PositionRotation>
				<X>-1287.10278</X>
				<Y>-2971.27686</Y>
				<Z>12.9385881</Z>
				<Pitch>51.7792091</Pitch>
				<Roll>-0.00127784465</Roll>
				<Yaw>59.1439857</Yaw>
			</PositionRotation>
			<Attachment isAttached="true">
				<AttachedTo>612443</AttachedTo>
				<BoneIndex>0</BoneIndex>
				<X>0.399999976</X>
				<Y>0</Y>
				<Z>-0.399999976</Z>
				<Pitch>51.7997818</Pitch>
				<Roll>0</Roll>
				<Yaw>0</Yaw>
			</Attachment>
		</Attachment>
		<Attachment>
			<ModelHash>0x46a578b5</ModelHash>
			<Type>3</Type>
			<Dynamic>false</Dynamic>
			<FrozenPos>true</FrozenPos>
			<HashName>prop_ld_rope_t</HashName>
			<InitialHandle>487515</InitialHandle>
			<ObjectProperties>
				<TextureVariation>0</TextureVariation>
			</ObjectProperties>
			<OpacityLevel>255</OpacityLevel>
			<LodDistance>16960</LodDistance>
			<IsVisible>true</IsVisible>
			<MaxHealth>1000</MaxHealth>
			<Health>1000</Health>
			<HasGravity>true</HasGravity>
			<IsOnFire>false</IsOnFire>
			<IsInvincible>true</IsInvincible>
			<IsBulletProof>false</IsBulletProof>
			<IsCollisionProof>true</IsCollisionProof>
			<IsExplosionProof>true</IsExplosionProof>
			<IsFireProof>true</IsFireProof>
			<IsMeleeProof>true</IsMeleeProof>
			<IsOnlyDamagedByPlayer>false</IsOnlyDamagedByPlayer>
			<PositionRotation>
				<X>-1286.91223</X>
				<Y>-2972.32251</Y>
				<Z>12.9388285</Z>
				<Pitch>-57.7202606</Pitch>
				<Roll>-0.00148516125</Roll>
				<Yaw>59.1417389</Yaw>
			</PositionRotation>
			<Attachment isAttached="true">
				<AttachedTo>612443</AttachedTo>
				<BoneIndex>0</BoneIndex>
				<X>-0.399999976</X>
				<Y>-0.699999928</Y>
				<Z>-0.399999976</Z>
				<Pitch>-57.6996918</Pitch>
				<Roll>0</Roll>
				<Yaw>0</Yaw>
			</Attachment>
		</Attachment>
		<Attachment>
			<ModelHash>0x46a578b5</ModelHash>
			<Type>3</Type>
			<Dynamic>false</Dynamic>
			<FrozenPos>true</FrozenPos>
			<HashName>prop_ld_rope_t</HashName>
			<InitialHandle>695387</InitialHandle>
			<ObjectProperties>
				<TextureVariation>0</TextureVariation>
			</ObjectProperties>
			<OpacityLevel>255</OpacityLevel>
			<LodDistance>16960</LodDistance>
			<IsVisible>true</IsVisible>
			<MaxHealth>1000</MaxHealth>
			<Health>1000</Health>
			<HasGravity>true</HasGravity>
			<IsOnFire>false</IsOnFire>
			<IsInvincible>true</IsInvincible>
			<IsBulletProof>false</IsBulletProof>
			<IsCollisionProof>true</IsCollisionProof>
			<IsExplosionProof>true</IsExplosionProof>
			<IsFireProof>true</IsFireProof>
			<IsMeleeProof>true</IsMeleeProof>
			<IsOnlyDamagedByPlayer>false</IsOnlyDamagedByPlayer>
			<PositionRotation>
				<X>-1287.51318</X>
				<Y>-2971.96362</Y>
				<Z>12.9385777</Z>
				<Pitch>52.8792</Pitch>
				<Roll>-0.0013114356</Roll>
				<Yaw>59.1440392</Yaw>
			</PositionRotation>
			<Attachment isAttached="true">
				<AttachedTo>612443</AttachedTo>
				<BoneIndex>0</BoneIndex>
				<X>-0.399999976</X>
				<Y>0</Y>
				<Z>-0.399999976</Z>
				<Pitch>52.899765</Pitch>
				<Roll>0</Roll>
				<Yaw>0</Yaw>
			</Attachment>
		</Attachment>
		<Attachment>
			<ModelHash>0x4e8f95a2</ModelHash>
			<Type>1</Type>
			<Dynamic>true</Dynamic>
			<FrozenPos>false</FrozenPos>
			<HashName>Husky</HashName>
			<InitialHandle>538715</InitialHandle>
			<TaskSequence>
				<Task>
					<Type>14</Type>
					<Duration>10000</Duration>
					<KeepTaskRunningAfterTime>1</KeepTaskRunningAfterTime>
					<IsLoopedTask>false</IsLoopedTask>
					<AnimDict>creatures@husky@move</AnimDict>
					<AnimName>gallop</AnimName>
					<Speed>4</Speed>
					<SpeedMultiplier>-4</SpeedMultiplier>
					<Flag>1</Flag>
					<LockPos>false</LockPos>
					<OverrideDurationToNormalSpeedAnimDuration>false</OverrideDurationToNormalSpeedAnimDuration>
				</Task>
			</TaskSequence>
			<PedProperties>
				<IsStill>true</IsStill>
				<CanRagdoll>false</CanRagdoll>
				<HasShortHeight>false</HasShortHeight>
				<Armour>0</Armour>
				<CurrentWeapon>0xe5b7de7a</CurrentWeapon>
				<PedProps>
					<_0>-1,-1</_0>
					<_1>-1,-1</_1>
					<_2>-1,-1</_2>
					<_3>-1,-1</_3>
					<_4>-1,-1</_4>
					<_5>-1,-1</_5>
					<_6>-1,-1</_6>
					<_7>-1,-1</_7>
					<_8>-1,-1</_8>
					<_9>-1,-1</_9>
				</PedProps>
				<PedComps>
					<_0>0,0</_0>
					<_1>0,0</_1>
					<_2>0,0</_2>
					<_3>0,0</_3>
					<_4>0,0</_4>
					<_5>0,0</_5>
					<_6>0,0</_6>
					<_7>0,0</_7>
					<_8>0,0</_8>
					<_9>0,0</_9>
					<_10>0,0</_10>
					<_11>0,0</_11>
				</PedComps>
				<RelationshipGroupAltered>true</RelationshipGroupAltered>
				<RelationshipGroup>0x2f000b85</RelationshipGroup>
				<ScenarioActive>false</ScenarioActive>
				<AnimActive>false</AnimActive>
			</PedProperties>
			<OpacityLevel>255</OpacityLevel>
			<LodDistance>16960</LodDistance>
			<IsVisible>true</IsVisible>
			<MaxHealth>99999</MaxHealth>
			<Health>99999</Health>
			<HasGravity>true</HasGravity>
			<IsOnFire>false</IsOnFire>
			<IsInvincible>true</IsInvincible>
			<IsBulletProof>false</IsBulletProof>
			<IsCollisionProof>true</IsCollisionProof>
			<IsExplosionProof>true</IsExplosionProof>
			<IsFireProof>true</IsFireProof>
			<IsMeleeProof>true</IsMeleeProof>
			<IsOnlyDamagedByPlayer>false</IsOnlyDamagedByPlayer>
			<PositionRotation>
				<X>-1291.85791</X>
				<Y>-2968.90186</Y>
				<Z>13.3365746</Z>
				<Pitch>-0.0217945371</Pitch>
				<Roll>-0.000828663062</Roll>
				<Yaw>59.1430817</Yaw>
			</PositionRotation>
			<Attachment isAttached="true">
				<AttachedTo>612443</AttachedTo>
				<BoneIndex>0</BoneIndex>
				<X>0</X>
				<Y>5.29999733</Y>
				<Z>0</Z>
				<Pitch>0</Pitch>
				<Roll>0</Roll>
				<Yaw>0</Yaw>
			</Attachment>
		</Attachment>
		<Attachment>
			<ModelHash>0x4e8f95a2</ModelHash>
			<Type>1</Type>
			<Dynamic>true</Dynamic>
			<FrozenPos>false</FrozenPos>
			<HashName>Husky</HashName>
			<InitialHandle>663643</InitialHandle>
			<TaskSequence>
				<Task>
					<Type>14</Type>
					<Duration>10000</Duration>
					<KeepTaskRunningAfterTime>1</KeepTaskRunningAfterTime>
					<IsLoopedTask>false</IsLoopedTask>
					<AnimDict>creatures@husky@move</AnimDict>
					<AnimName>gallop</AnimName>
					<Speed>4</Speed>
					<SpeedMultiplier>-4</SpeedMultiplier>
					<Flag>1</Flag>
					<LockPos>false</LockPos>
					<OverrideDurationToNormalSpeedAnimDuration>false</OverrideDurationToNormalSpeedAnimDuration>
				</Task>
			</TaskSequence>
			<PedProperties>
				<IsStill>true</IsStill>
				<CanRagdoll>false</CanRagdoll>
				<HasShortHeight>false</HasShortHeight>
				<Armour>0</Armour>
				<CurrentWeapon>0xe5b7de7a</CurrentWeapon>
				<PedProps>
					<_0>-1,-1</_0>
					<_1>-1,-1</_1>
					<_2>-1,-1</_2>
					<_3>-1,-1</_3>
					<_4>-1,-1</_4>
					<_5>-1,-1</_5>
					<_6>-1,-1</_6>
					<_7>-1,-1</_7>
					<_8>-1,-1</_8>
					<_9>-1,-1</_9>
				</PedProps>
				<PedComps>
					<_0>0,0</_0>
					<_1>0,0</_1>
					<_2>0,0</_2>
					<_3>0,0</_3>
					<_4>0,0</_4>
					<_5>0,0</_5>
					<_6>0,0</_6>
					<_7>0,0</_7>
					<_8>0,0</_8>
					<_9>0,0</_9>
					<_10>0,0</_10>
					<_11>0,0</_11>
				</PedComps>
				<RelationshipGroupAltered>true</RelationshipGroupAltered>
				<RelationshipGroup>0x2f000b85</RelationshipGroup>
				<ScenarioActive>false</ScenarioActive>
				<AnimActive>false</AnimActive>
			</PedProperties>
			<OpacityLevel>255</OpacityLevel>
			<LodDistance>16960</LodDistance>
			<IsVisible>true</IsVisible>
			<MaxHealth>99999</MaxHealth>
			<Health>99999</Health>
			<HasGravity>true</HasGravity>
			<IsOnFire>false</IsOnFire>
			<IsInvincible>true</IsInvincible>
			<IsBulletProof>false</IsBulletProof>
			<IsCollisionProof>true</IsCollisionProof>
			<IsExplosionProof>true</IsExplosionProof>
			<IsFireProof>true</IsFireProof>
			<IsMeleeProof>true</IsMeleeProof>
			<IsOnlyDamagedByPlayer>false</IsOnlyDamagedByPlayer>
			<PositionRotation>
				<X>-1290.68958</X>
				<Y>-2970.06567</Y>
				<Z>13.3371773</Z>
				<Pitch>-0.0217945371</Pitch>
				<Roll>-0.000828663062</Roll>
				<Yaw>59.1430817</Yaw>
			</PositionRotation>
			<Attachment isAttached="true">
				<AttachedTo>612443</AttachedTo>
				<BoneIndex>0</BoneIndex>
				<X>-0.399999976</X>
				<Y>3.69999862</Y>
				<Z>0</Z>
				<Pitch>0</Pitch>
				<Roll>0</Roll>
				<Yaw>0</Yaw>
			</Attachment>
		</Attachment>
		<Attachment>
			<ModelHash>0x4e8f95a2</ModelHash>
			<Type>1</Type>
			<Dynamic>true</Dynamic>
			<FrozenPos>false</FrozenPos>
			<HashName>Husky</HashName>
			<InitialHandle>696923</InitialHandle>
			<TaskSequence>
				<Task>
					<Type>14</Type>
					<Duration>10000</Duration>
					<KeepTaskRunningAfterTime>1</KeepTaskRunningAfterTime>
					<IsLoopedTask>false</IsLoopedTask>
					<AnimDict>creatures@husky@move</AnimDict>
					<AnimName>gallop</AnimName>
					<Speed>4</Speed>
					<SpeedMultiplier>-4</SpeedMultiplier>
					<Flag>1</Flag>
					<LockPos>false</LockPos>
					<OverrideDurationToNormalSpeedAnimDuration>false</OverrideDurationToNormalSpeedAnimDuration>
				</Task>
			</TaskSequence>
			<PedProperties>
				<IsStill>true</IsStill>
				<CanRagdoll>false</CanRagdoll>
				<HasShortHeight>false</HasShortHeight>
				<Armour>0</Armour>
				<CurrentWeapon>0xe5b7de7a</CurrentWeapon>
				<PedProps>
					<_0>-1,-1</_0>
					<_1>-1,-1</_1>
					<_2>-1,-1</_2>
					<_3>-1,-1</_3>
					<_4>-1,-1</_4>
					<_5>-1,-1</_5>
					<_6>-1,-1</_6>
					<_7>-1,-1</_7>
					<_8>-1,-1</_8>
					<_9>-1,-1</_9>
				</PedProps>
				<PedComps>
					<_0>0,0</_0>
					<_1>0,0</_1>
					<_2>0,0</_2>
					<_3>0,0</_3>
					<_4>0,0</_4>
					<_5>0,0</_5>
					<_6>0,0</_6>
					<_7>0,0</_7>
					<_8>0,0</_8>
					<_9>0,0</_9>
					<_10>0,0</_10>
					<_11>0,0</_11>
				</PedComps>
				<RelationshipGroupAltered>true</RelationshipGroupAltered>
				<RelationshipGroup>0x2f000b85</RelationshipGroup>
				<ScenarioActive>false</ScenarioActive>
				<AnimActive>false</AnimActive>
			</PedProperties>
			<OpacityLevel>255</OpacityLevel>
			<LodDistance>16960</LodDistance>
			<IsVisible>true</IsVisible>
			<MaxHealth>99999</MaxHealth>
			<Health>99999</Health>
			<HasGravity>true</HasGravity>
			<IsOnFire>false</IsOnFire>
			<IsInvincible>true</IsInvincible>
			<IsBulletProof>false</IsBulletProof>
			<IsCollisionProof>true</IsCollisionProof>
			<IsExplosionProof>true</IsExplosionProof>
			<IsFireProof>true</IsFireProof>
			<IsMeleeProof>true</IsMeleeProof>
			<IsOnlyDamagedByPlayer>false</IsOnlyDamagedByPlayer>
			<PositionRotation>
				<X>-1290.22791</X>
				<Y>-2969.29321</Y>
				<Z>13.3371906</Z>
				<Pitch>-0.0217945371</Pitch>
				<Roll>-0.000828663062</Roll>
				<Yaw>59.1430817</Yaw>
			</PositionRotation>
			<Attachment isAttached="true">
				<AttachedTo>612443</AttachedTo>
				<BoneIndex>0</BoneIndex>
				<X>0.49999997</X>
				<Y>3.69999862</Y>
				<Z>0</Z>
				<Pitch>0</Pitch>
				<Roll>0</Roll>
				<Yaw>0</Yaw>
			</Attachment>
		</Attachment>
		<Attachment>
			<ModelHash>0x4e8f95a2</ModelHash>
			<Type>1</Type>
			<Dynamic>true</Dynamic>
			<FrozenPos>false</FrozenPos>
			<HashName>Husky</HashName>
			<InitialHandle>657499</InitialHandle>
			<TaskSequence>
				<Task>
					<Type>14</Type>
					<Duration>10000</Duration>
					<KeepTaskRunningAfterTime>1</KeepTaskRunningAfterTime>
					<IsLoopedTask>false</IsLoopedTask>
					<AnimDict>creatures@husky@move</AnimDict>
					<AnimName>canter</AnimName>
					<Speed>4</Speed>
					<SpeedMultiplier>-4</SpeedMultiplier>
					<Flag>1</Flag>
					<LockPos>false</LockPos>
					<OverrideDurationToNormalSpeedAnimDuration>false</OverrideDurationToNormalSpeedAnimDuration>
				</Task>
			</TaskSequence>
			<PedProperties>
				<IsStill>true</IsStill>
				<CanRagdoll>false</CanRagdoll>
				<HasShortHeight>false</HasShortHeight>
				<Armour>0</Armour>
				<CurrentWeapon>0xe5b7de7a</CurrentWeapon>
				<PedProps>
					<_0>-1,-1</_0>
					<_1>-1,-1</_1>
					<_2>-1,-1</_2>
					<_3>-1,-1</_3>
					<_4>-1,-1</_4>
					<_5>-1,-1</_5>
					<_6>-1,-1</_6>
					<_7>-1,-1</_7>
					<_8>-1,-1</_8>
					<_9>-1,-1</_9>
				</PedProps>
				<PedComps>
					<_0>0,0</_0>
					<_1>0,0</_1>
					<_2>0,0</_2>
					<_3>0,0</_3>
					<_4>0,0</_4>
					<_5>0,0</_5>
					<_6>0,0</_6>
					<_7>0,0</_7>
					<_8>0,0</_8>
					<_9>0,0</_9>
					<_10>0,0</_10>
					<_11>0,0</_11>
				</PedComps>
				<RelationshipGroupAltered>true</RelationshipGroupAltered>
				<RelationshipGroup>0x2f000b85</RelationshipGroup>
				<ScenarioActive>false</ScenarioActive>
				<AnimActive>true</AnimActive>
				<AnimDict>creatures@husky@move</AnimDict>
				<AnimName>gallop</AnimName>
			</PedProperties>
			<OpacityLevel>255</OpacityLevel>
			<LodDistance>16960</LodDistance>
			<IsVisible>true</IsVisible>
			<MaxHealth>99999</MaxHealth>
			<Health>99999</Health>
			<HasGravity>true</HasGravity>
			<IsOnFire>false</IsOnFire>
			<IsInvincible>true</IsInvincible>
			<IsBulletProof>false</IsBulletProof>
			<IsCollisionProof>true</IsCollisionProof>
			<IsExplosionProof>true</IsExplosionProof>
			<IsFireProof>true</IsFireProof>
			<IsMeleeProof>true</IsMeleeProof>
			<IsOnlyDamagedByPlayer>false</IsOnlyDamagedByPlayer>
			<PositionRotation>
				<X>-1288.94031</X>
				<Y>-2970.0625</Y>
				<Z>13.3377609</Z>
				<Pitch>-0.0217945371</Pitch>
				<Roll>-0.000828663062</Roll>
				<Yaw>59.1430817</Yaw>
			</PositionRotation>
			<Attachment isAttached="true">
				<AttachedTo>612443</AttachedTo>
				<BoneIndex>0</BoneIndex>
				<X>0.49999997</X>
				<Y>2.20000005</Y>
				<Z>0</Z>
				<Pitch>0</Pitch>
				<Roll>0</Roll>
				<Yaw>0</Yaw>
			</Attachment>
		</Attachment>
		<Attachment>
			<ModelHash>0x4e8f95a2</ModelHash>
			<Type>1</Type>
			<Dynamic>true</Dynamic>
			<FrozenPos>false</FrozenPos>
			<HashName>Husky</HashName>
			<InitialHandle>700507</InitialHandle>
			<TaskSequence>
				<Task>
					<Type>14</Type>
					<Duration>10000</Duration>
					<KeepTaskRunningAfterTime>1</KeepTaskRunningAfterTime>
					<IsLoopedTask>false</IsLoopedTask>
					<AnimDict>creatures@husky@move</AnimDict>
					<AnimName>canter</AnimName>
					<Speed>4</Speed>
					<SpeedMultiplier>-4</SpeedMultiplier>
					<Flag>1</Flag>
					<LockPos>false</LockPos>
					<OverrideDurationToNormalSpeedAnimDuration>false</OverrideDurationToNormalSpeedAnimDuration>
				</Task>
			</TaskSequence>
			<PedProperties>
				<IsStill>true</IsStill>
				<CanRagdoll>false</CanRagdoll>
				<HasShortHeight>false</HasShortHeight>
				<Armour>0</Armour>
				<CurrentWeapon>0xe5b7de7a</CurrentWeapon>
				<PedProps>
					<_0>-1,-1</_0>
					<_1>-1,-1</_1>
					<_2>-1,-1</_2>
					<_3>-1,-1</_3>
					<_4>-1,-1</_4>
					<_5>-1,-1</_5>
					<_6>-1,-1</_6>
					<_7>-1,-1</_7>
					<_8>-1,-1</_8>
					<_9>-1,-1</_9>
				</PedProps>
				<PedComps>
					<_0>0,0</_0>
					<_1>0,0</_1>
					<_2>0,0</_2>
					<_3>0,0</_3>
					<_4>0,0</_4>
					<_5>0,0</_5>
					<_6>0,0</_6>
					<_7>0,0</_7>
					<_8>0,0</_8>
					<_9>0,0</_9>
					<_10>0,0</_10>
					<_11>0,0</_11>
				</PedComps>
				<RelationshipGroupAltered>true</RelationshipGroupAltered>
				<RelationshipGroup>0x2f000b85</RelationshipGroup>
				<ScenarioActive>false</ScenarioActive>
				<AnimActive>true</AnimActive>
				<AnimDict>creatures@husky@move</AnimDict>
				<AnimName>gallop</AnimName>
			</PedProperties>
			<OpacityLevel>255</OpacityLevel>
			<LodDistance>16960</LodDistance>
			<IsVisible>true</IsVisible>
			<MaxHealth>99999</MaxHealth>
			<Health>99999</Health>
			<HasGravity>true</HasGravity>
			<IsOnFire>false</IsOnFire>
			<IsInvincible>true</IsInvincible>
			<IsBulletProof>false</IsBulletProof>
			<IsCollisionProof>true</IsCollisionProof>
			<IsExplosionProof>true</IsExplosionProof>
			<IsFireProof>true</IsFireProof>
			<IsMeleeProof>true</IsMeleeProof>
			<IsOnlyDamagedByPlayer>false</IsOnlyDamagedByPlayer>
			<PositionRotation>
				<X>-1289.45313</X>
				<Y>-2970.9209</Y>
				<Z>13.3377466</Z>
				<Pitch>-0.0217945371</Pitch>
				<Roll>-0.000828663062</Roll>
				<Yaw>59.1430817</Yaw>
			</PositionRotation>
			<Attachment isAttached="true">
				<AttachedTo>612443</AttachedTo>
				<BoneIndex>0</BoneIndex>
				<X>-0.49999997</X>
				<Y>2.20000005</Y>
				<Z>0</Z>
				<Pitch>0</Pitch>
				<Roll>0</Roll>
				<Yaw>0</Yaw>
			</Attachment>
		</Attachment>
		<Attachment>
			<ModelHash>0x6b73bb05</ModelHash>
			<Type>3</Type>
			<Dynamic>false</Dynamic>
			<FrozenPos>true</FrozenPos>
			<HashName>prop_cs_para_ropes</HashName>
			<InitialHandle>689755</InitialHandle>
			<ObjectProperties>
				<TextureVariation>0</TextureVariation>
			</ObjectProperties>
			<OpacityLevel>255</OpacityLevel>
			<LodDistance>16960</LodDistance>
			<IsVisible>true</IsVisible>
			<MaxHealth>1000</MaxHealth>
			<Health>1000</Health>
			<HasGravity>true</HasGravity>
			<IsOnFire>false</IsOnFire>
			<IsInvincible>true</IsInvincible>
			<IsBulletProof>false</IsBulletProof>
			<IsCollisionProof>true</IsCollisionProof>
			<IsExplosionProof>true</IsExplosionProof>
			<IsFireProof>true</IsFireProof>
			<IsMeleeProof>true</IsMeleeProof>
			<IsOnlyDamagedByPlayer>false</IsOnlyDamagedByPlayer>
			<PositionRotation>
				<X>-1289.40088</X>
				<Y>-2971.41821</Y>
				<Z>13.5378885</Z>
				<Pitch>90</Pitch>
				<Roll>-127.856956</Roll>
				<Yaw>0</Yaw>
			</PositionRotation>
			<Attachment isAttached="true">
				<AttachedTo>612443</AttachedTo>
				<BoneIndex>0</BoneIndex>
				<X>-0.899999857</X>
				<Y>1.90000021</Y>
				<Z>0.199999988</Z>
				<Pitch>89.9999542</Pitch>
				<Roll>3.47497844e-05</Roll>
				<Yaw>173.000015</Yaw>
			</Attachment>
		</Attachment>
		<Attachment>
			<ModelHash>0x6b73bb05</ModelHash>
			<Type>3</Type>
			<Dynamic>false</Dynamic>
			<FrozenPos>true</FrozenPos>
			<HashName>prop_cs_para_ropes</HashName>
			<InitialHandle>679771</InitialHandle>
			<ObjectProperties>
				<TextureVariation>0</TextureVariation>
			</ObjectProperties>
			<OpacityLevel>255</OpacityLevel>
			<LodDistance>16960</LodDistance>
			<IsVisible>true</IsVisible>
			<MaxHealth>1000</MaxHealth>
			<Health>1000</Health>
			<HasGravity>true</HasGravity>
			<IsOnFire>false</IsOnFire>
			<IsInvincible>true</IsInvincible>
			<IsBulletProof>false</IsBulletProof>
			<IsCollisionProof>true</IsCollisionProof>
			<IsExplosionProof>true</IsExplosionProof>
			<IsFireProof>true</IsFireProof>
			<IsMeleeProof>true</IsMeleeProof>
			<IsOnlyDamagedByPlayer>false</IsOnlyDamagedByPlayer>
			<PositionRotation>
				<X>-1288.51208</X>
				<Y>-2969.73584</Y>
				<Z>13.1378794</Z>
				<Pitch>-87.5204544</Pitch>
				<Roll>0.0562624671</Roll>
				<Yaw>68.1991959</Yaw>
			</PositionRotation>
			<Attachment isAttached="true">
				<AttachedTo>612443</AttachedTo>
				<BoneIndex>0</BoneIndex>
				<X>0.99999994</X>
				<Y>2.00000024</Y>
				<Z>-0.199999988</Z>
				<Pitch>-87.5000839</Pitch>
				<Roll>-1.96695328e-06</Roll>
				<Yaw>8.99999905</Yaw>
			</Attachment>
		</Attachment>
		<Attachment>
			<ModelHash>0xb34e141d</ModelHash>
			<Type>3</Type>
			<Dynamic>false</Dynamic>
			<FrozenPos>true</FrozenPos>
			<HashName>prop_wheel_hub_01</HashName>
			<InitialHandle>674395</InitialHandle>
			<ObjectProperties>
				<TextureVariation>0</TextureVariation>
			</ObjectProperties>
			<OpacityLevel>255</OpacityLevel>
			<LodDistance>16960</LodDistance>
			<IsVisible>true</IsVisible>
			<MaxHealth>1000</MaxHealth>
			<Health>1000</Health>
			<HasGravity>true</HasGravity>
			<IsOnFire>false</IsOnFire>
			<IsInvincible>true</IsInvincible>
			<IsBulletProof>false</IsBulletProof>
			<IsCollisionProof>true</IsCollisionProof>
			<IsExplosionProof>true</IsExplosionProof>
			<IsFireProof>true</IsFireProof>
			<IsMeleeProof>true</IsMeleeProof>
			<IsOnlyDamagedByPlayer>false</IsOnlyDamagedByPlayer>
			<PositionRotation>
				<X>-1287.58435</X>
				<Y>-2971.79199</Y>
				<Z>13.9678507</Z>
				<Pitch>-15.2705793</Pitch>
				<Roll>-0.000821299676</Roll>
				<Yaw>59.1427765</Yaw>
			</PositionRotation>
			<Attachment isAttached="true">
				<AttachedTo>612443</AttachedTo>
				<BoneIndex>24</BoneIndex>
				<X>0</X>
				<Y>0</Y>
				<Z>0</Z>
				<Pitch>0</Pitch>
				<Roll>0</Roll>
				<Yaw>0</Yaw>
			</Attachment>
		</Attachment>
		<Attachment>
			<ModelHash>0xb650118a</ModelHash>
			<Type>3</Type>
			<Dynamic>false</Dynamic>
			<FrozenPos>true</FrozenPos>
			<HashName>prop_air_trailer_3b</HashName>
			<InitialHandle>328795</InitialHandle>
			<ObjectProperties>
				<TextureVariation>0</TextureVariation>
			</ObjectProperties>
			<OpacityLevel>255</OpacityLevel>
			<LodDistance>16960</LodDistance>
			<IsVisible>true</IsVisible>
			<MaxHealth>1000</MaxHealth>
			<Health>1000</Health>
			<HasGravity>true</HasGravity>
			<IsOnFire>false</IsOnFire>
			<IsInvincible>true</IsInvincible>
			<IsBulletProof>false</IsBulletProof>
			<IsCollisionProof>true</IsCollisionProof>
			<IsExplosionProof>true</IsExplosionProof>
			<IsFireProof>true</IsFireProof>
			<IsMeleeProof>true</IsMeleeProof>
			<IsOnlyDamagedByPlayer>false</IsOnlyDamagedByPlayer>
			<PositionRotation>
				<X>-1284.73267</X>
				<Y>-2973.15894</Y>
				<Z>12.9396601</Z>
				<Pitch>-0.000792514533</Pitch>
				<Roll>0.0205666162</Roll>
				<Yaw>149.142975</Yaw>
			</PositionRotation>
			<Attachment isAttached="true">
				<AttachedTo>612443</AttachedTo>
				<BoneIndex>0</BoneIndex>
				<X>0</X>
				<Y>-2.99999905</Y>
				<Z>-0.399999976</Z>
				<Pitch>0</Pitch>
				<Roll>0</Roll>
				<Yaw>89.9999924</Yaw>
			</Attachment>
		</Attachment>
		<Attachment>
			<ModelHash>0xfb31584b</ModelHash>
			<Type>3</Type>
			<Dynamic>false</Dynamic>
			<FrozenPos>true</FrozenPos>
			<HashName>ex_prop_crate_money_bc</HashName>
			<InitialHandle>701019</InitialHandle>
			<ObjectProperties>
				<TextureVariation>0</TextureVariation>
			</ObjectProperties>
			<OpacityLevel>255</OpacityLevel>
			<LodDistance>16960</LodDistance>
			<IsVisible>true</IsVisible>
			<MaxHealth>1000</MaxHealth>
			<Health>1000</Health>
			<HasGravity>true</HasGravity>
			<IsOnFire>false</IsOnFire>
			<IsInvincible>true</IsInvincible>
			<IsBulletProof>false</IsBulletProof>
			<IsCollisionProof>true</IsCollisionProof>
			<IsExplosionProof>true</IsExplosionProof>
			<IsFireProof>true</IsFireProof>
			<IsMeleeProof>true</IsMeleeProof>
			<IsOnlyDamagedByPlayer>false</IsOnlyDamagedByPlayer>
			<PositionRotation>
				<X>-1284.81873</X>
				<Y>-2973.10742</Y>
				<Z>13.6396236</Z>
				<Pitch>-0.000792514533</Pitch>
				<Roll>0.0205666162</Roll>
				<Yaw>149.142975</Yaw>
			</PositionRotation>
			<Attachment isAttached="true">
				<AttachedTo>612443</AttachedTo>
				<BoneIndex>0</BoneIndex>
				<X>0</X>
				<Y>-2.89999938</Y>
				<Z>0.299999982</Z>
				<Pitch>0</Pitch>
				<Roll>0</Roll>
				<Yaw>89.9999924</Yaw>
			</Attachment>
		</Attachment>
		<Attachment>
			<ModelHash>0x46a578b5</ModelHash>
			<Type>3</Type>
			<Dynamic>false</Dynamic>
			<FrozenPos>true</FrozenPos>
			<HashName>prop_ld_rope_t</HashName>
			<InitialHandle>632667</InitialHandle>
			<ObjectProperties>
				<TextureVariation>0</TextureVariation>
			</ObjectProperties>
			<OpacityLevel>255</OpacityLevel>
			<LodDistance>16960</LodDistance>
			<IsVisible>true</IsVisible>
			<MaxHealth>1000</MaxHealth>
			<Health>1000</Health>
			<HasGravity>true</HasGravity>
			<IsOnFire>false</IsOnFire>
			<IsInvincible>true</IsInvincible>
			<IsBulletProof>false</IsBulletProof>
			<IsCollisionProof>true</IsCollisionProof>
			<IsExplosionProof>true</IsExplosionProof>
			<IsFireProof>true</IsFireProof>
			<IsMeleeProof>true</IsMeleeProof>
			<IsOnlyDamagedByPlayer>false</IsOnlyDamagedByPlayer>
			<PositionRotation>
				<X>-1288.74487</X>
				<Y>-2970.02783</Y>
				<Z>13.6778555</Z>
				<Pitch>-0.0205666181</Pitch>
				<Roll>-90.0007858</Roll>
				<Yaw>59.1429863</Yaw>
			</PositionRotation>
			<Attachment isAttached="true">
				<AttachedTo>612443</AttachedTo>
				<BoneIndex>0</BoneIndex>
				<X>0.629999697</X>
				<Y>2.04999971</Y>
				<Z>0.339999974</Z>
				<Pitch>0</Pitch>
				<Roll>-90</Roll>
				<Yaw>0</Yaw>
			</Attachment>
		</Attachment>
		<Attachment>
			<ModelHash>0xdd486535</ModelHash>
			<Type>3</Type>
			<Dynamic>false</Dynamic>
			<FrozenPos>true</FrozenPos>
			<HashName>p_ld_heist_bag_s_2</HashName>
			<InitialHandle>676955</InitialHandle>
			<ObjectProperties>
				<TextureVariation>0</TextureVariation>
			</ObjectProperties>
			<OpacityLevel>255</OpacityLevel>
			<LodDistance>16960</LodDistance>
			<IsVisible>true</IsVisible>
			<MaxHealth>1000</MaxHealth>
			<Health>1000</Health>
			<HasGravity>true</HasGravity>
			<IsOnFire>false</IsOnFire>
			<IsInvincible>true</IsInvincible>
			<IsBulletProof>false</IsBulletProof>
			<IsCollisionProof>true</IsCollisionProof>
			<IsExplosionProof>true</IsExplosionProof>
			<IsFireProof>true</IsFireProof>
			<IsMeleeProof>true</IsMeleeProof>
			<IsOnlyDamagedByPlayer>false</IsOnlyDamagedByPlayer>
			<PositionRotation>
				<X>-1285.53186</X>
				<Y>-2972.33203</Y>
				<Z>13.4492655</Z>
				<Pitch>-0.0205678325</Pitch>
				<Roll>14.9992075</Roll>
				<Yaw>59.1429863</Yaw>
			</PositionRotation>
			<Attachment isAttached="true">
				<AttachedTo>612443</AttachedTo>
				<BoneIndex>0</BoneIndex>
				<X>0.299999982</X>
				<Y>-1.89000034</Y>
				<Z>0.109999985</Z>
				<Pitch>0</Pitch>
				<Roll>14.9999981</Roll>
				<Yaw>0</Yaw>
			</Attachment>
		</Attachment>
		<Attachment>
			<ModelHash>0xd92f6238</ModelHash>
			<Type>3</Type>
			<Dynamic>false</Dynamic>
			<FrozenPos>true</FrozenPos>
			<HashName>p_ld_heist_bag_s_pro</HashName>
			<InitialHandle>703579</InitialHandle>
			<ObjectProperties>
				<TextureVariation>0</TextureVariation>
			</ObjectProperties>
			<OpacityLevel>255</OpacityLevel>
			<LodDistance>16960</LodDistance>
			<IsVisible>true</IsVisible>
			<MaxHealth>1000</MaxHealth>
			<Health>1000</Health>
			<HasGravity>true</HasGravity>
			<IsOnFire>false</IsOnFire>
			<IsInvincible>true</IsInvincible>
			<IsBulletProof>false</IsBulletProof>
			<IsCollisionProof>true</IsCollisionProof>
			<IsExplosionProof>true</IsExplosionProof>
			<IsFireProof>true</IsFireProof>
			<IsMeleeProof>true</IsMeleeProof>
			<IsOnlyDamagedByPlayer>false</IsOnlyDamagedByPlayer>
			<PositionRotation>
				<X>-1285.88904</X>
				<Y>-2972.96899</Y>
				<Z>13.3792629</Z>
				<Pitch>-0.0205678325</Pitch>
				<Roll>14.9992075</Roll>
				<Yaw>59.1429863</Yaw>
			</PositionRotation>
			<Attachment isAttached="true">
				<AttachedTo>612443</AttachedTo>
				<BoneIndex>0</BoneIndex>
				<X>-0.429999858</X>
				<Y>-1.91000032</Y>
				<Z>0.0400000066</Z>
				<Pitch>0</Pitch>
				<Roll>14.999999</Roll>
				<Yaw>0</Yaw>
			</Attachment>
		</Attachment>
		<Attachment>
			<ModelHash>0x4eb1e082</ModelHash>
			<Type>3</Type>
			<Dynamic>false</Dynamic>
			<FrozenPos>true</FrozenPos>
			<HashName>hei_prop_carrier_light_01</HashName>
			<InitialHandle>712283</InitialHandle>
			<ObjectProperties>
				<TextureVariation>0</TextureVariation>
			</ObjectProperties>
			<OpacityLevel>255</OpacityLevel>
			<LodDistance>16960</LodDistance>
			<IsVisible>true</IsVisible>
			<MaxHealth>1000</MaxHealth>
			<Health>1000</Health>
			<HasGravity>true</HasGravity>
			<IsOnFire>false</IsOnFire>
			<IsInvincible>true</IsInvincible>
			<IsBulletProof>false</IsBulletProof>
			<IsCollisionProof>false</IsCollisionProof>
			<IsExplosionProof>true</IsExplosionProof>
			<IsFireProof>false</IsFireProof>
			<IsMeleeProof>true</IsMeleeProof>
			<IsOnlyDamagedByPlayer>false</IsOnlyDamagedByPlayer>
			<PositionRotation>
				<X>-1285.38525</X>
				<Y>-2972.8855</Y>
				<Z>14.4394073</Z>
				<Pitch>0.0205666218</Pitch>
				<Roll>0.000792502135</Roll>
				<Yaw>-120.856979</Yaw>
			</PositionRotation>
			<Attachment isAttached="true">
				<AttachedTo>612443</AttachedTo>
				<BoneIndex>0</BoneIndex>
				<X>-0.099999994</X>
				<Y>-2.29999995</Y>
				<Z>1.10000002</Z>
				<Pitch>0</Pitch>
				<Roll>0</Roll>
				<Yaw>-179.999985</Yaw>
			</Attachment>
		</Attachment>
		<Attachment>
			<ModelHash>0xb7e2ddaf</ModelHash>
			<Type>3</Type>
			<Dynamic>false</Dynamic>
			<FrozenPos>true</FrozenPos>
			<HashName>w_sg_heavyshotgun</HashName>
			<InitialHandle>692315</InitialHandle>
			<ObjectProperties>
				<TextureVariation>0</TextureVariation>
			</ObjectProperties>
			<OpacityLevel>255</OpacityLevel>
			<LodDistance>16960</LodDistance>
			<IsVisible>true</IsVisible>
			<MaxHealth>1000</MaxHealth>
			<Health>1000</Health>
			<HasGravity>true</HasGravity>
			<IsOnFire>false</IsOnFire>
			<IsInvincible>true</IsInvincible>
			<IsBulletProof>false</IsBulletProof>
			<IsCollisionProof>true</IsCollisionProof>
			<IsExplosionProof>true</IsExplosionProof>
			<IsFireProof>true</IsFireProof>
			<IsMeleeProof>true</IsMeleeProof>
			<IsOnlyDamagedByPlayer>false</IsOnlyDamagedByPlayer>
			<PositionRotation>
				<X>-1286.96997</X>
				<Y>-2971.83374</Y>
				<Z>13.7687263</Z>
				<Pitch>-0.0205364563</Pitch>
				<Roll>-84.0007935</Roll>
				<Yaw>59.1430092</Yaw>
			</PositionRotation>
			<Attachment isAttached="true">
				<AttachedTo>612443</AttachedTo>
				<BoneIndex>0</BoneIndex>
				<X>-0.00999999978</X>
				<Y>-0.399999887</Y>
				<Z>0.430000037</Z>
				<Pitch>3.06367874e-05</Pitch>
				<Roll>-84</Roll>
				<Yaw>1.81794167e-05</Yaw>
			</Attachment>
		</Attachment>
		<Attachment>
			<ModelHash>0xb63f6584</ModelHash>
			<Type>3</Type>
			<Dynamic>false</Dynamic>
			<FrozenPos>true</FrozenPos>
			<HashName>prop_rope_family_3</HashName>
			<InitialHandle>712027</InitialHandle>
			<ObjectProperties>
				<TextureVariation>0</TextureVariation>
			</ObjectProperties>
			<OpacityLevel>255</OpacityLevel>
			<LodDistance>16960</LodDistance>
			<IsVisible>true</IsVisible>
			<MaxHealth>1000</MaxHealth>
			<Health>1000</Health>
			<HasGravity>true</HasGravity>
			<IsOnFire>false</IsOnFire>
			<IsInvincible>true</IsInvincible>
			<IsBulletProof>false</IsBulletProof>
			<IsCollisionProof>true</IsCollisionProof>
			<IsExplosionProof>true</IsExplosionProof>
			<IsFireProof>true</IsFireProof>
			<IsMeleeProof>true</IsMeleeProof>
			<IsOnlyDamagedByPlayer>false</IsOnlyDamagedByPlayer>
			<PositionRotation>
				<X>-1291.96948</X>
				<Y>-2968.83496</Y>
				<Z>13.4266338</Z>
				<Pitch>0.000788886799</Pitch>
				<Roll>-39.3209724</Roll>
				<Yaw>-30.8570004</Yaw>
			</PositionRotation>
			<Attachment isAttached="true">
				<AttachedTo>612443</AttachedTo>
				<BoneIndex>0</BoneIndex>
				<X>0</X>
				<Y>5.43000031</Y>
				<Z>0.0899999887</Z>
				<Pitch>0</Pitch>
				<Roll>-39.3004189</Roll>
				<Yaw>-90</Yaw>
			</Attachment>
		</Attachment>
		<Attachment>
			<ModelHash>0xb63f6584</ModelHash>
			<Type>3</Type>
			<Dynamic>false</Dynamic>
			<FrozenPos>true</FrozenPos>
			<HashName>prop_rope_family_3</HashName>
			<InitialHandle>671323</InitialHandle>
			<ObjectProperties>
				<TextureVariation>0</TextureVariation>
			</ObjectProperties>
			<OpacityLevel>255</OpacityLevel>
			<LodDistance>16960</LodDistance>
			<IsVisible>true</IsVisible>
			<MaxHealth>1000</MaxHealth>
			<Health>1000</Health>
			<HasGravity>true</HasGravity>
			<IsOnFire>false</IsOnFire>
			<IsInvincible>true</IsInvincible>
			<IsBulletProof>false</IsBulletProof>
			<IsCollisionProof>true</IsCollisionProof>
			<IsExplosionProof>true</IsExplosionProof>
			<IsFireProof>true</IsFireProof>
			<IsMeleeProof>true</IsMeleeProof>
			<IsOnlyDamagedByPlayer>false</IsOnlyDamagedByPlayer>
			<PositionRotation>
				<X>-1290.86633</X>
				<Y>-2969.97168</Y>
				<Z>13.4171772</Z>
				<Pitch>0.000789740589</Pitch>
				<Roll>-38.0205612</Roll>
				<Yaw>-30.8569927</Yaw>
			</PositionRotation>
			<Attachment isAttached="true">
				<AttachedTo>612443</AttachedTo>
				<BoneIndex>0</BoneIndex>
				<X>-0.409999877</X>
				<Y>3.899997</Y>
				<Z>0.0799999908</Z>
				<Pitch>0</Pitch>
				<Roll>-37.9999962</Roll>
				<Yaw>-89.9999924</Yaw>
			</Attachment>
		</Attachment>
		<Attachment>
			<ModelHash>0xb63f6584</ModelHash>
			<Type>3</Type>
			<Dynamic>false</Dynamic>
			<FrozenPos>true</FrozenPos>
			<HashName>prop_rope_family_3</HashName>
			<InitialHandle>711771</InitialHandle>
			<ObjectProperties>
				<TextureVariation>0</TextureVariation>
			</ObjectProperties>
			<OpacityLevel>255</OpacityLevel>
			<LodDistance>16960</LodDistance>
			<IsVisible>true</IsVisible>
			<MaxHealth>1000</MaxHealth>
			<Health>1000</Health>
			<HasGravity>true</HasGravity>
			<IsOnFire>false</IsOnFire>
			<IsInvincible>true</IsInvincible>
			<IsBulletProof>false</IsBulletProof>
			<IsCollisionProof>true</IsCollisionProof>
			<IsExplosionProof>true</IsExplosionProof>
			<IsFireProof>true</IsFireProof>
			<IsMeleeProof>true</IsMeleeProof>
			<IsOnlyDamagedByPlayer>false</IsOnlyDamagedByPlayer>
			<PositionRotation>
				<X>-1290.37744</X>
				<Y>-2969.13403</Y>
				<Z>13.4671869</Z>
				<Pitch>0.0007923019</Pitch>
				<Roll>-32.0205612</Roll>
				<Yaw>-30.8570004</Yaw>
			</PositionRotation>
			<Attachment isAttached="true">
				<AttachedTo>612443</AttachedTo>
				<BoneIndex>0</BoneIndex>
				<X>0.559999764</X>
				<Y>3.90999675</Y>
				<Z>0.12999998</Z>
				<Pitch>0</Pitch>
				<Roll>-32</Roll>
				<Yaw>-89.9999924</Yaw>
			</Attachment>
		</Attachment>
		<Attachment>
			<ModelHash>0xb63f6584</ModelHash>
			<Type>3</Type>
			<Dynamic>false</Dynamic>
			<FrozenPos>true</FrozenPos>
			<HashName>prop_rope_family_3</HashName>
			<InitialHandle>700251</InitialHandle>
			<ObjectProperties>
				<TextureVariation>0</TextureVariation>
			</ObjectProperties>
			<OpacityLevel>255</OpacityLevel>
			<LodDistance>16960</LodDistance>
			<IsVisible>true</IsVisible>
			<MaxHealth>1000</MaxHealth>
			<Health>1000</Health>
			<HasGravity>true</HasGravity>
			<IsOnFire>false</IsOnFire>
			<IsInvincible>true</IsInvincible>
			<IsBulletProof>false</IsBulletProof>
			<IsCollisionProof>true</IsCollisionProof>
			<IsExplosionProof>true</IsExplosionProof>
			<IsFireProof>true</IsFireProof>
			<IsMeleeProof>true</IsMeleeProof>
			<IsOnlyDamagedByPlayer>false</IsOnlyDamagedByPlayer>
			<PositionRotation>
				<X>-1289.62488</X>
				<Y>-2970.81836</Y>
				<Z>13.4077148</Z>
				<Pitch>0.00079144811</Pitch>
				<Roll>-45.0205574</Roll>
				<Yaw>-30.8569965</Yaw>
			</PositionRotation>
			<Attachment isAttached="true">
				<AttachedTo>612443</AttachedTo>
				<BoneIndex>0</BoneIndex>
				<X>-0.50000006</X>
				<Y>2.39999986</Y>
				<Z>0.0699999928</Z>
				<Pitch>0</Pitch>
				<Roll>-44.9999962</Roll>
				<Yaw>-89.9999924</Yaw>
			</Attachment>
		</Attachment>
		<Attachment>
			<ModelHash>0xb63f6584</ModelHash>
			<Type>3</Type>
			<Dynamic>false</Dynamic>
			<FrozenPos>true</FrozenPos>
			<HashName>prop_rope_family_3</HashName>
			<InitialHandle>349019</InitialHandle>
			<ObjectProperties>
				<TextureVariation>0</TextureVariation>
			</ObjectProperties>
			<OpacityLevel>255</OpacityLevel>
			<LodDistance>16960</LodDistance>
			<IsVisible>true</IsVisible>
			<MaxHealth>1000</MaxHealth>
			<Health>1000</Health>
			<HasGravity>true</HasGravity>
			<IsOnFire>false</IsOnFire>
			<IsInvincible>true</IsInvincible>
			<IsBulletProof>false</IsBulletProof>
			<IsCollisionProof>true</IsCollisionProof>
			<IsExplosionProof>true</IsExplosionProof>
			<IsFireProof>true</IsFireProof>
			<IsMeleeProof>true</IsMeleeProof>
			<IsOnlyDamagedByPlayer>false</IsOnlyDamagedByPlayer>
			<PositionRotation>
				<X>-1289.10681</X>
				<Y>-2969.95142</Y>
				<Z>13.4277287</Z>
				<Pitch>0.000789740589</Pitch>
				<Roll>-39.0205536</Roll>
				<Yaw>-30.8569927</Yaw>
			</PositionRotation>
			<Attachment isAttached="true">
				<AttachedTo>612443</AttachedTo>
				<BoneIndex>0</BoneIndex>
				<X>0.509999812</X>
				<Y>2.39999819</Y>
				<Z>0.0899999887</Z>
				<Pitch>0</Pitch>
				<Roll>-38.9999962</Roll>
				<Yaw>-89.9999924</Yaw>
			</Attachment>
		</Attachment>
		<Attachment>
			<ModelHash>0x46a578b5</ModelHash>
			<Type>3</Type>
			<Dynamic>false</Dynamic>
			<FrozenPos>true</FrozenPos>
			<HashName>prop_ld_rope_t</HashName>
			<InitialHandle>308059</InitialHandle>
			<ObjectProperties>
				<TextureVariation>0</TextureVariation>
			</ObjectProperties>
			<OpacityLevel>255</OpacityLevel>
			<LodDistance>16960</LodDistance>
			<IsVisible>true</IsVisible>
			<MaxHealth>1000</MaxHealth>
			<Health>1000</Health>
			<HasGravity>true</HasGravity>
			<IsOnFire>false</IsOnFire>
			<IsInvincible>true</IsInvincible>
			<IsBulletProof>false</IsBulletProof>
			<IsCollisionProof>true</IsCollisionProof>
			<IsExplosionProof>true</IsExplosionProof>
			<IsFireProof>true</IsFireProof>
			<IsMeleeProof>true</IsMeleeProof>
			<IsOnlyDamagedByPlayer>false</IsOnlyDamagedByPlayer>
			<PositionRotation>
				<X>-1289.99841</X>
				<Y>-2969.2207</Y>
				<Z>13.6873217</Z>
				<Pitch>-0.0205666162</Pitch>
				<Roll>-90.0007782</Roll>
				<Yaw>59.1429863</Yaw>
			</PositionRotation>
			<Attachment isAttached="true">
				<AttachedTo>612443</AttachedTo>
				<BoneIndex>0</BoneIndex>
				<X>0.67999965</X>
				<Y>3.5399971</Y>
				<Z>0.349999934</Z>
				<Pitch>0</Pitch>
				<Roll>-89.9999924</Roll>
				<Yaw>0</Yaw>
			</Attachment>
		</Attachment>
		<Attachment>
			<ModelHash>0x99100663</ModelHash>
			<Type>3</Type>
			<Dynamic>false</Dynamic>
			<FrozenPos>true</FrozenPos>
			<HashName>port_xr_lifep</HashName>
			<InitialHandle>711003</InitialHandle>
			<ObjectProperties>
				<TextureVariation>0</TextureVariation>
			</ObjectProperties>
			<OpacityLevel>255</OpacityLevel>
			<LodDistance>16960</LodDistance>
			<IsVisible>true</IsVisible>
			<MaxHealth>1000</MaxHealth>
			<Health>1000</Health>
			<HasGravity>true</HasGravity>
			<IsOnFire>false</IsOnFire>
			<IsInvincible>true</IsInvincible>
			<IsBulletProof>false</IsBulletProof>
			<IsCollisionProof>true</IsCollisionProof>
			<IsExplosionProof>true</IsExplosionProof>
			<IsFireProof>true</IsFireProof>
			<IsMeleeProof>true</IsMeleeProof>
			<IsOnlyDamagedByPlayer>false</IsOnlyDamagedByPlayer>
			<PositionRotation>
				<X>-1285.55688</X>
				<Y>-2972.78296</Y>
				<Z>14.2393351</Z>
				<Pitch>0.0205666218</Pitch>
				<Roll>0.000792502135</Roll>
				<Yaw>-120.856979</Yaw>
			</PositionRotation>
			<Attachment isAttached="true">
				<AttachedTo>612443</AttachedTo>
				<BoneIndex>0</BoneIndex>
				<X>-0.099999994</X>
				<Y>-2.10000014</Y>
				<Z>0.899999976</Z>
				<Pitch>0</Pitch>
				<Roll>0</Roll>
				<Yaw>-179.999985</Yaw>
			</Attachment>
		</Attachment>
		<Attachment>
			<ModelHash>0x28781518</ModelHash>
			<Type>3</Type>
			<Dynamic>false</Dynamic>
			<FrozenPos>true</FrozenPos>
			<HashName>prop_ld_health_pack</HashName>
			<InitialHandle>634715</InitialHandle>
			<ObjectProperties>
				<TextureVariation>0</TextureVariation>
			</ObjectProperties>
			<OpacityLevel>255</OpacityLevel>
			<LodDistance>16960</LodDistance>
			<IsVisible>true</IsVisible>
			<MaxHealth>1000</MaxHealth>
			<Health>1000</Health>
			<HasGravity>true</HasGravity>
			<IsOnFire>false</IsOnFire>
			<IsInvincible>true</IsInvincible>
			<IsBulletProof>false</IsBulletProof>
			<IsCollisionProof>true</IsCollisionProof>
			<IsExplosionProof>true</IsExplosionProof>
			<IsFireProof>true</IsFireProof>
			<IsMeleeProof>true</IsMeleeProof>
			<IsOnlyDamagedByPlayer>false</IsOnlyDamagedByPlayer>
			<PositionRotation>
				<X>-1285.67712</X>
				<Y>-2972.59448</Y>
				<Z>13.6392651</Z>
				<Pitch>-0.0205666181</Pitch>
				<Roll>-0.000792510225</Roll>
				<Yaw>59.1429863</Yaw>
			</PositionRotation>
			<Attachment isAttached="true">
				<AttachedTo>612443</AttachedTo>
				<BoneIndex>0</BoneIndex>
				<X>0</X>
				<Y>-1.90000021</Y>
				<Z>0.299999982</Z>
				<Pitch>0</Pitch>
				<Roll>0</Roll>
				<Yaw>0</Yaw>
			</Attachment>
		</Attachment>
		<Attachment>
			<ModelHash>0x57358f6b</ModelHash>
			<Type>3</Type>
			<Dynamic>false</Dynamic>
			<FrozenPos>true</FrozenPos>
			<HashName>prop_food_bag2</HashName>
			<InitialHandle>691547</InitialHandle>
			<ObjectProperties>
				<TextureVariation>0</TextureVariation>
			</ObjectProperties>
			<OpacityLevel>255</OpacityLevel>
			<LodDistance>16960</LodDistance>
			<IsVisible>true</IsVisible>
			<MaxHealth>1000</MaxHealth>
			<Health>1000</Health>
			<HasGravity>true</HasGravity>
			<IsOnFire>false</IsOnFire>
			<IsInvincible>true</IsInvincible>
			<IsBulletProof>false</IsBulletProof>
			<IsCollisionProof>true</IsCollisionProof>
			<IsExplosionProof>true</IsExplosionProof>
			<IsFireProof>true</IsFireProof>
			<IsMeleeProof>true</IsMeleeProof>
			<IsOnlyDamagedByPlayer>false</IsOnlyDamagedByPlayer>
			<PositionRotation>
				<X>-1287.03394</X>
				<Y>-2971.55103</Y>
				<Z>13.5686579</Z>
				<Pitch>-0.0205666181</Pitch>
				<Roll>-0.000792510225</Roll>
				<Yaw>59.1429863</Yaw>
			</PositionRotation>
			<Attachment isAttached="true">
				<AttachedTo>612443</AttachedTo>
				<BoneIndex>0</BoneIndex>
				<X>0.199999988</X>
				<Y>-0.199999988</Y>
				<Z>0.230000019</Z>
				<Pitch>0</Pitch>
				<Roll>0</Roll>
				<Yaw>0</Yaw>
			</Attachment>
		</Attachment>
		<Attachment>
			<ModelHash>0x223bddc4</ModelHash>
			<Type>3</Type>
			<Dynamic>false</Dynamic>
			<FrozenPos>true</FrozenPos>
			<HashName>w_sb_gusenberg</HashName>
			<InitialHandle>683611</InitialHandle>
			<ObjectProperties>
				<TextureVariation>0</TextureVariation>
			</ObjectProperties>
			<OpacityLevel>255</OpacityLevel>
			<LodDistance>16960</LodDistance>
			<IsVisible>true</IsVisible>
			<MaxHealth>1000</MaxHealth>
			<Health>1000</Health>
			<HasGravity>true</HasGravity>
			<IsOnFire>false</IsOnFire>
			<IsInvincible>true</IsInvincible>
			<IsBulletProof>false</IsBulletProof>
			<IsCollisionProof>true</IsCollisionProof>
			<IsExplosionProof>true</IsExplosionProof>
			<IsFireProof>true</IsFireProof>
			<IsMeleeProof>true</IsMeleeProof>
			<IsOnlyDamagedByPlayer>false</IsOnlyDamagedByPlayer>
			<PositionRotation>
				<X>-1287.12329</X>
				<Y>-2971.48584</Y>
				<Z>13.8986177</Z>
				<Pitch>-0.0205665529</Pitch>
				<Roll>-69.0007782</Roll>
				<Yaw>59.1429863</Yaw>
			</PositionRotation>
			<Attachment isAttached="true">
				<AttachedTo>612443</AttachedTo>
				<BoneIndex>0</BoneIndex>
				<X>0.210000038</X>
				<Y>-0.0899999887</Y>
				<Z>0.559999764</Z>
				<Pitch>0</Pitch>
				<Roll>-68.9999924</Roll>
				<Yaw>0</Yaw>
			</Attachment>
		</Attachment>
		<Attachment>
			<ModelHash>0xa0bd351e</ModelHash>
			<Type>3</Type>
			<Dynamic>false</Dynamic>
			<FrozenPos>true</FrozenPos>
			<HashName>w_sg_bullpupshotgun</HashName>
			<InitialHandle>692059</InitialHandle>
			<ObjectProperties>
				<TextureVariation>0</TextureVariation>
			</ObjectProperties>
			<OpacityLevel>255</OpacityLevel>
			<LodDistance>16960</LodDistance>
			<IsVisible>true</IsVisible>
			<MaxHealth>1000</MaxHealth>
			<Health>1000</Health>
			<HasGravity>true</HasGravity>
			<IsOnFire>false</IsOnFire>
			<IsInvincible>true</IsInvincible>
			<IsBulletProof>false</IsBulletProof>
			<IsCollisionProof>true</IsCollisionProof>
			<IsExplosionProof>true</IsExplosionProof>
			<IsFireProof>true</IsFireProof>
			<IsMeleeProof>true</IsMeleeProof>
			<IsOnlyDamagedByPlayer>false</IsOnlyDamagedByPlayer>
			<PositionRotation>
				<X>-1287.07336</X>
				<Y>-2971.59741</Y>
				<Z>13.8486528</Z>
				<Pitch>-0.0100403773</Pitch>
				<Roll>-72.9820175</Roll>
				<Yaw>122.142982</Yaw>
			</PositionRotation>
			<Attachment isAttached="true">
				<AttachedTo>612443</AttachedTo>
				<BoneIndex>0</BoneIndex>
				<X>0.139999986</X>
				<Y>-0.190000013</Y>
				<Z>0.509999812</Z>
				<Pitch>0</Pitch>
				<Roll>-72.9999924</Roll>
				<Yaw>63</Yaw>
			</Attachment>
		</Attachment>
		<Attachment>
			<ModelHash>0x8d1b8c15</ModelHash>
			<Type>3</Type>
			<Dynamic>false</Dynamic>
			<FrozenPos>true</FrozenPos>
			<HashName>p_cs_rope_tie_01_s</HashName>
			<InitialHandle>669787</InitialHandle>
			<ObjectProperties>
				<TextureVariation>0</TextureVariation>
			</ObjectProperties>
			<OpacityLevel>255</OpacityLevel>
			<LodDistance>16960</LodDistance>
			<IsVisible>true</IsVisible>
			<MaxHealth>1000</MaxHealth>
			<Health>1000</Health>
			<HasGravity>true</HasGravity>
			<IsOnFire>false</IsOnFire>
			<IsInvincible>true</IsInvincible>
			<IsBulletProof>false</IsBulletProof>
			<IsCollisionProof>false</IsCollisionProof>
			<IsExplosionProof>true</IsExplosionProof>
			<IsFireProof>true</IsFireProof>
			<IsMeleeProof>true</IsMeleeProof>
			<IsOnlyDamagedByPlayer>false</IsOnlyDamagedByPlayer>
			<PositionRotation>
				<X>-1287.54797</X>
				<Y>-2971.82617</Y>
				<Z>13.9385433</Z>
				<Pitch>0.397797674</Pitch>
				<Roll>3.02047753</Roll>
				<Yaw>145.142838</Yaw>
			</PositionRotation>
			<Attachment isAttached="true">
				<AttachedTo>612443</AttachedTo>
				<BoneIndex>0</BoneIndex>
				<X>-0.299999893</X>
				<Y>0.0999997631</Y>
				<Z>0.599999905</Z>
				<Pitch>0.400022566</Pitch>
				<Roll>3.00001621</Roll>
				<Yaw>85.9999924</Yaw>
			</Attachment>
		</Attachment>
	</SpoonerAttachments>
</Vehicle>
