{"children":[{"target_version":"0.35","offset":{"y":-0.8,"x":0.0,"z":0.3},"type":"OBJECT","options":{"weight":0.0,"object_tint":0,"is_melee_proof":false,"is_invincible":true,"bone_index":0,"is_visible":true,"is_light_on":true,"is_bullet_proof":false,"is_explosion_proof":false,"is_fire_proof":false,"lod_distance":16960,"has_gravity":true,"is_networked":true,"buoyancy":0.0,"use_soft_pinning":true,"is_driver_visible":true,"is_dynamic":true,"has_collision":true,"gravity":0.0,"alpha":255,"is_attached":true,"is_mission_entity":true},"blip_icon":1,"blip_color":2,"num_bones":0,"world_rotation":{"y":-0.464708,"x":0.311728,"z":-25.78001},"children":{},"hash":-1003273441,"rotation":{"y":0,"x":0,"z":0},"position":{"y":-659.329651,"x":-96.876556,"z":50.421928},"rotation_order":2,"model":"v_res_tre_laundrybasket","name":"v_res_tre_laundrybasket"},{"target_version":"0.35","options":{"weight":0.0,"object_tint":0,"is_melee_proof":false,"is_invincible":true,"bone_index":0,"is_visible":true,"is_light_on":true,"is_bullet_proof":false,"is_explosion_proof":false,"is_fire_proof":false,"lod_distance":16960,"has_gravity":true,"is_networked":true,"gravity":0.0,"use_soft_pinning":true,"buoyancy":0.0,"is_dynamic":true,"has_collision":true,"is_driver_visible":true,"alpha":255,"is_attached":true,"is_mission_entity":true},"ped_attributes":{"armor":0,"components":{"_10":{"drawable_variation":0,"palette_variation":0,"texture_variation":0},"_0":{"drawable_variation":0,"palette_variation":1,"texture_variation":0},"_1":{"drawable_variation":0,"palette_variation":0,"texture_variation":0},"_2":{"drawable_variation":0,"palette_variation":0,"texture_variation":0},"_3":{"drawable_variation":0,"palette_variation":1,"texture_variation":0},"_11":{"drawable_variation":0,"palette_variation":0,"texture_variation":0},"_5":{"drawable_variation":0,"palette_variation":0,"texture_variation":0},"_4":{"drawable_variation":0,"palette_variation":1,"texture_variation":0},"_8":{"drawable_variation":0,"palette_variation":1,"texture_variation":0},"_9":{"drawable_variation":0,"palette_variation":0,"texture_variation":0},"_6":{"drawable_variation":0,"palette_variation":0,"texture_variation":0},"_7":{"drawable_variation":0,"palette_variation":0,"texture_variation":0}},"weapon":{},"seat":-3,"props":{"_0":{"drawable_variation":-1,"texture_variation":-1},"_1":{"drawable_variation":-1,"texture_variation":-1},"_3":{"drawable_variation":-1,"texture_variation":-1},"_2":{"drawable_variation":-1,"texture_variation":-1},"_5":{"drawable_variation":-1,"texture_variation":-1},"_4":{"drawable_variation":-1,"texture_variation":-1},"_8":{"drawable_variation":-1,"texture_variation":-1},"_9":{"drawable_variation":-1,"texture_variation":-1},"_6":{"drawable_variation":-1,"texture_variation":-1},"_7":{"drawable_variation":-1,"texture_variation":-1}},"ignore_events":false},"model":"a_c_pug","rotation_order":2,"blip_icon":1,"offset":{"y":-0.8,"x":0.0,"z":0.6},"world_rotation":{"y":-0.42139,"x":-0.368184,"z":49.217365},"type":"PED","children":{},"hash":1832265812,"rotation":{"y":0,"x":0,"z":75},"position":{"y":-659.330078,"x":-96.879456,"z":50.721916},"blip_color":2,"num_bones":60,"name":"Pug"}],"hash":2069146067,"rotation":{"y":0,"x":0,"z":0},"position":{"y":-658.60968,"x":-96.527344,"z":50.100868},"blip_handle":70255504,"target_version":"0.35","offset":{"y":0,"x":0,"z":0},"author":"Slaytooth","model":"oppressor2","rotation_order":2,"version":"Constructor 0.36b4 / 0.35 / 0.36b1","created":"2023-04-02T22:42:46Z","num_bones":58,"vehicle_attributes":{"wheels":{"tires_burst":{},"tire_smoke_color":{"r":255,"g":255,"b":255},"wheel_type":6},"doors":{"broken":{},"open":{"backright":false,"frontright":false,"trunk2":false,"trunk":false,"frontleft":false,"backleft":false,"hood":false}},"extras":{},"windows":{"rolled_down":{},"broken":{"rearright":false,"rear":false,"frontright":false,"frontleft":false,"front":false,"midright":false,"rearleft":false}},"neon":{"lights":{"right":false,"left":false,"back":false,"front":false},"color":{}},"paint":{"primary":{"pearlescent_color":-1,"color":-1,"is_custom":false,"paint_type":7,"custom_color":{},"vehicle_standard_color":62},"livery2_legacy":-1,"livery":-1,"fade":0.0,"dirt_level":0.0,"livery_legacy":-1,"vehicle_custom_color":{"r":0,"g":16,"b":41},"interior_color":93,"dashboard_color":93,"extra_colors":{"pearlescent":87,"wheel":112},"color_combo":-1,"secondary":{"color":-1,"is_custom":false,"paint_type":7,"custom_color":{},"vehicle_standard_color":0}},"mods":{"_10":-1,"_25":-1,"_1":-1,"_46":-1,"_26":-1,"_23":-1,"_40":-1,"_29":-1,"_39":-1,"_17":false,"_21":false,"_27":-1,"_38":-1,"_41":-1,"_24":-1,"_9":-1,"_45":-1,"_7":-1,"_28":-1,"_19":false,"_15":-1,"_35":-1,"_0":-1,"_2":-1,"_4":-1,"_3":-1,"_36":-1,"_12":-1,"_16":-1,"_11":-1,"_47":-1,"_18":false,"_33":-1,"_20":false,"_13":-1,"_37":-1,"_34":-1,"_30":-1,"_43":-1,"_14":-1,"_5":-1,"_22":false,"_49":-1,"_44":-1,"_31":-1,"_48":-1,"_8":-1,"_42":-1,"_6":-1,"_32":-1},"options":{"license_plate_text":"68ABU925","siren":false,"radio_loud":false,"bulletproof_tires":false,"license_plate_type":0,"search_light":false,"emergency_lights":false,"engine_running":true,"window_tint":-1},"headlights":{"headlights_type":false,"headlight_color":-1,"headlights_color":0}},"world_rotation":{"y":-0.452023,"x":0.392774,"z":-25.792437},"type":"VEHICLE","blip_sprite":1,"blip_color":2,"options":{"weight":0.0,"object_tint":0,"is_melee_proof":false,"is_invincible":true,"bone_index":0,"is_visible":true,"is_light_on":true,"is_bullet_proof":false,"is_explosion_proof":false,"is_fire_proof":false,"lod_distance":16960,"has_gravity":true,"is_networked":true,"buoyancy":0.0,"use_soft_pinning":true,"is_driver_visible":true,"is_dynamic":true,"has_collision":true,"gravity":0.0,"alpha":255,"is_attached":false,"is_mission_entity":true},"name":"Precious Cargo"}