{"target_version":"3.27b2","children":[{"rotation_axis":2,"model":"xs_prop_chips_tube_wl","target_version":"3.27b2","num_bones":0,"children":{},"parents_initial_handle":246288,"offset":{"z":0,"x":-10.399994,"y":-29.400074},"id":1072,"rotation":{"z":0,"x":0,"y":0},"type":"OBJECT","name":"xs_prop_chips_tube_wl","world_rotation":{"z":32.411892,"x":-0.062175,"y":-0.018427},"hash":2534896289,"initial_handle":132375,"position":{"z":34.677311,"x":-1387.57019,"y":-2901.44214},"options":{"has_gravity":true,"is_melee_proof":true,"alpha":255,"is_visible":true,"max_health":1000,"is_light_on":true,"is_on_fire":false,"lod_distance":16960,"has_collision":true,"is_attached":true,"bone_index":0,"is_mission_entity":true,"is_bullet_proof":false,"is_dynamic":false,"is_invincible":true,"is_fire_proof":true,"is_frozen":true,"is_explosion_proof":true,"use_soft_pinning":true,"health":1000,"is_networked":true}},{"rotation_axis":2,"model":"xs_prop_chips_tube_wl","target_version":"3.27b2","num_bones":0,"children":{},"parents_initial_handle":246288,"offset":{"z":0,"x":10.400003,"y":-29.400076},"id":1073,"rotation":{"z":0,"x":0,"y":0},"type":"OBJECT","name":"xs_prop_chips_tube_wl","world_rotation":{"z":32.411892,"x":-0.062175,"y":-0.018427},"hash":2534896289,"initial_handle":338199,"position":{"z":34.683998,"x":-1370.0105,"y":-2890.29321},"options":{"has_gravity":true,"is_melee_proof":true,"alpha":255,"is_visible":true,"max_health":1000,"is_light_on":true,"is_on_fire":false,"lod_distance":16960,"has_collision":true,"is_attached":true,"bone_index":0,"is_mission_entity":true,"is_bullet_proof":false,"is_dynamic":false,"is_invincible":true,"is_fire_proof":true,"is_frozen":true,"is_explosion_proof":true,"use_soft_pinning":true,"health":1000,"is_networked":true}},{"rotation_axis":2,"model":"apa_prop_aptest","target_version":"3.27b2","num_bones":0,"children":{},"parents_initial_handle":246288,"offset":{"z":0,"x":-10.400002,"y":-16.400026},"id":1074,"rotation":{"z":0,"x":-89.999992,"y":0},"type":"OBJECT","name":"apa_prop_aptest","world_rotation":{"z":0,"x":-89.940651,"y":-32.411884},"hash":340496207,"initial_handle":315690,"position":{"z":34.663204,"x":-1394.53821,"y":-2890.46729},"options":{"has_gravity":true,"is_melee_proof":true,"alpha":255,"is_visible":true,"max_health":1000,"is_light_on":true,"is_on_fire":false,"lod_distance":16960,"has_collision":true,"is_attached":true,"bone_index":0,"is_mission_entity":true,"is_bullet_proof":false,"is_dynamic":false,"is_invincible":true,"is_fire_proof":true,"is_frozen":true,"is_explosion_proof":true,"use_soft_pinning":true,"health":1000,"is_networked":true}},{"rotation_axis":2,"model":"apa_prop_aptest","target_version":"3.27b2","num_bones":0,"children":{},"parents_initial_handle":246288,"offset":{"z":0,"x":10.400003,"y":-16.400026},"id":1075,"rotation":{"z":0,"x":-89.999992,"y":0},"type":"OBJECT","name":"apa_prop_aptest","world_rotation":{"z":0,"x":-89.940651,"y":-32.411884},"hash":340496207,"initial_handle":409898,"position":{"z":34.669891,"x":-1376.97852,"y":-2879.31836},"options":{"has_gravity":true,"is_melee_proof":true,"alpha":255,"is_visible":true,"max_health":1000,"is_light_on":true,"is_on_fire":false,"lod_distance":16960,"has_collision":true,"is_attached":true,"bone_index":0,"is_mission_entity":true,"is_bullet_proof":false,"is_dynamic":false,"is_invincible":true,"is_fire_proof":true,"is_frozen":true,"is_explosion_proof":true,"use_soft_pinning":true,"health":1000,"is_networked":true}},{"rotation_axis":2,"model":"prop_ind_barge_02","target_version":"3.27b2","num_bones":0,"children":{},"parents_initial_handle":246288,"offset":{"z":-0.,"x":0,"y":-10.700005},"id":1076,"rotation":{"z":0,"x":0,"y":-179.999985},"type":"OBJECT","name":"prop_ind_barge_02","world_rotation":{"z":32.411896,"x":-0.062175,"y":179.981583},"hash":3616603294,"initial_handle":119321,"position":{"z":34.660362,"x":-1388.8136,"y":-2880.08081},"options":{"has_gravity":true,"is_melee_proof":true,"alpha":255,"is_visible":true,"max_health":1000,"is_light_on":true,"is_on_fire":false,"lod_distance":16960,"has_collision":false,"is_attached":true,"bone_index":0,"is_mission_entity":true,"is_bullet_proof":false,"is_dynamic":false,"is_invincible":true,"is_fire_proof":true,"is_frozen":true,"is_explosion_proof":true,"use_soft_pinning":true,"health":1000,"is_networked":true}},{"rotation_axis":2,"model":"prop_ind_barge_02","target_version":"3.27b2","num_bones":0,"children":{},"parents_initial_handle":246288,"offset":{"z":0.,"x":0,"y":-10.700005},"id":1077,"rotation":{"z":0,"x":0,"y":0},"type":"OBJECT","name":"prop_ind_barge_02","world_rotation":{"z":32.411892,"x":-0.062175,"y":-0.018427},"hash":3616603294,"initial_handle":737305,"position":{"z":34.660362,"x":-1388.8136,"y":-2880.08081},"options":{"has_gravity":true,"is_melee_proof":true,"alpha":255,"is_visible":true,"max_health":1000,"is_light_on":true,"is_on_fire":false,"lod_distance":16960,"has_collision":false,"is_attached":true,"bone_index":0,"is_mission_entity":true,"is_bullet_proof":false,"is_dynamic":false,"is_invincible":true,"is_fire_proof":true,"is_frozen":true,"is_explosion_proof":true,"use_soft_pinning":true,"health":1000,"is_networked":true}},{"rotation_axis":2,"model":"xs_wasteland_pitstop","target_version":"3.27b2","num_bones":0,"children":{},"parents_initial_handle":246288,"offset":{"z":3.,"x":0,"y":-5.899997},"id":1078,"rotation":{"z":59.999996,"x":-61.999996,"y":0},"type":"OBJECT","name":"xs_wasteland_pitstop","world_rotation":{"z":92.495987,"x":-62.047005,"y":0.095211},"hash":2913569852,"initial_handle":562217,"position":{"z":37.655151,"x":-1391.38904,"y":-2876.02637},"options":{"has_gravity":true,"is_melee_proof":true,"alpha":255,"is_visible":true,"max_health":1000,"is_light_on":true,"is_on_fire":false,"lod_distance":16960,"has_collision":false,"is_attached":true,"bone_index":0,"is_mission_entity":true,"is_bullet_proof":false,"is_dynamic":false,"is_invincible":true,"is_fire_proof":true,"is_frozen":true,"is_explosion_proof":true,"use_soft_pinning":true,"health":1000,"is_networked":true}},{"rotation_axis":2,"model":"xs_wasteland_pitstop","target_version":"3.27b2","num_bones":0,"children":{},"parents_initial_handle":246288,"offset":{"z":2.999999,"x":0,"y":-5.899999},"id":1079,"rotation":{"z":59.999992,"x":-152.999985,"y":0},"type":"OBJECT","name":"xs_wasteland_pitstop","world_rotation":{"z":-87.610802,"x":-26.952957,"y":179.949921},"hash":2913569852,"initial_handle":122665,"position":{"z":37.655151,"x":-1391.38904,"y":-2876.02637},"options":{"has_gravity":true,"is_melee_proof":true,"alpha":255,"is_visible":true,"max_health":1000,"is_light_on":true,"is_on_fire":false,"lod_distance":16960,"has_collision":false,"is_attached":true,"bone_index":0,"is_mission_entity":true,"is_bullet_proof":false,"is_dynamic":false,"is_invincible":true,"is_fire_proof":true,"is_frozen":true,"is_explosion_proof":true,"use_soft_pinning":true,"health":1000,"is_networked":true}},{"rotation_axis":2,"model":"xs_wasteland_pitstop","target_version":"3.27b2","num_bones":0,"children":{},"parents_initial_handle":246288,"offset":{"z":2.3,"x":0,"y":-5.899997},"id":1080,"rotation":{"z":124.000053,"x":61.999992,"y":-0.000008},"type":"OBJECT","name":"xs_wasteland_pitstop","world_rotation":{"z":156.295532,"x":62.019413,"y":0.131821},"hash":2913569852,"initial_handle":693289,"position":{"z":36.955151,"x":-1391.38843,"y":-2876.02686},"options":{"has_gravity":true,"is_melee_proof":true,"alpha":255,"is_visible":true,"max_health":1000,"is_light_on":true,"is_on_fire":false,"lod_distance":16960,"has_collision":false,"is_attached":true,"bone_index":0,"is_mission_entity":true,"is_bullet_proof":false,"is_dynamic":false,"is_invincible":true,"is_fire_proof":true,"is_frozen":true,"is_explosion_proof":true,"use_soft_pinning":true,"health":1000,"is_networked":true}},{"rotation_axis":2,"model":"xs_wasteland_pitstop","target_version":"3.27b2","num_bones":0,"children":{},"parents_initial_handle":246288,"offset":{"z":2.400001,"x":0,"y":-5.899999},"id":1081,"rotation":{"z":123.999992,"x":152.999985,"y":-0.},"type":"OBJECT","name":"xs_wasteland_pitstop","world_rotation":{"z":-23.556593,"x":26.980509,"y":179.930588},"hash":2913569852,"initial_handle":765993,"position":{"z":37.055153,"x":-1391.38843,"y":-2876.02661},"options":{"has_gravity":true,"is_melee_proof":true,"alpha":255,"is_visible":true,"max_health":1000,"is_light_on":true,"is_on_fire":false,"lod_distance":16960,"has_collision":false,"is_attached":true,"bone_index":0,"is_mission_entity":true,"is_bullet_proof":false,"is_dynamic":false,"is_invincible":true,"is_fire_proof":true,"is_frozen":true,"is_explosion_proof":true,"use_soft_pinning":true,"health":1000,"is_networked":true}},{"rotation_axis":2,"model":"imp_prop_ie_carelev01","target_version":"3.27b2","num_bones":0,"children":{},"parents_initial_handle":246288,"offset":{"z":0,"x":-10.400003,"y":-42.699921},"id":1082,"rotation":{"z":0,"x":89.999992,"y":0},"type":"OBJECT","name":"imp_prop_ie_carelev01","world_rotation":{"z":0,"x":89.940651,"y":32.411884},"hash":3651154009,"initial_handle":285781,"position":{"z":34.691742,"x":-1380.44141,"y":-2912.66992},"options":{"has_gravity":true,"is_melee_proof":true,"alpha":255,"is_visible":true,"max_health":1000,"is_light_on":true,"is_on_fire":false,"lod_distance":16960,"has_collision":true,"is_attached":true,"bone_index":0,"is_mission_entity":true,"is_bullet_proof":false,"is_dynamic":false,"is_invincible":true,"is_fire_proof":true,"is_frozen":true,"is_explosion_proof":true,"use_soft_pinning":true,"health":1000,"is_networked":true}},{"rotation_axis":2,"model":"imp_prop_ie_carelev01","target_version":"3.27b2","num_bones":0,"children":{},"parents_initial_handle":246288,"offset":{"z":0,"x":10.400003,"y":-42.69091},"id":1083,"rotation":{"z":0,"x":89.999992,"y":0},"type":"OBJECT","name":"imp_prop_ie_carelev01","world_rotation":{"z":0,"x":89.940651,"y":32.411884},"hash":3651154009,"initial_handle":323157,"position":{"z":34.698422,"x":-1362.8866,"y":-2901.51343},"options":{"has_gravity":true,"is_melee_proof":true,"alpha":255,"is_visible":true,"max_health":1000,"is_light_on":true,"is_on_fire":false,"lod_distance":16960,"has_collision":true,"is_attached":true,"bone_index":0,"is_mission_entity":true,"is_bullet_proof":false,"is_dynamic":false,"is_invincible":true,"is_fire_proof":true,"is_frozen":true,"is_explosion_proof":true,"use_soft_pinning":true,"health":1000,"is_networked":true}},{"rotation_axis":2,"model":"xs_prop_arena_pipe_track_s_01b","target_version":"3.27b2","num_bones":4,"children":{},"parents_initial_handle":246288,"offset":{"z":-1.3,"x":-10.400003,"y":-42.399925},"id":1084,"rotation":{"z":0,"x":0,"y":0},"type":"OBJECT","name":"xs_prop_arena_pipe_track_s_01b","world_rotation":{"z":32.411892,"x":-0.062175,"y":-0.018427},"hash":656278478,"initial_handle":287331,"position":{"z":33.391419,"x":-1380.60107,"y":-2912.41772},"options":{"has_gravity":true,"is_melee_proof":true,"alpha":255,"is_visible":true,"max_health":1000,"is_light_on":true,"is_on_fire":false,"lod_distance":16960,"has_collision":true,"is_attached":true,"bone_index":0,"is_mission_entity":true,"is_bullet_proof":false,"is_dynamic":false,"is_invincible":true,"is_fire_proof":true,"is_frozen":true,"is_explosion_proof":true,"use_soft_pinning":true,"health":1000,"is_networked":true}},{"rotation_axis":2,"model":"xs_prop_arena_pipe_track_s_01b","target_version":"3.27b2","num_bones":4,"children":{},"parents_initial_handle":246288,"offset":{"z":-1.3,"x":10.400003,"y":-42.399925},"id":1085,"rotation":{"z":0,"x":0,"y":0},"type":"OBJECT","name":"xs_prop_arena_pipe_track_s_01b","world_rotation":{"z":32.411892,"x":-0.062175,"y":-0.018427},"hash":656278478,"initial_handle":331033,"position":{"z":33.398106,"x":-1363.04138,"y":-2901.2688},"options":{"has_gravity":true,"is_melee_proof":true,"alpha":255,"is_visible":true,"max_health":1000,"is_light_on":true,"is_on_fire":false,"lod_distance":16960,"has_collision":true,"is_attached":true,"bone_index":0,"is_mission_entity":true,"is_bullet_proof":false,"is_dynamic":false,"is_invincible":true,"is_fire_proof":true,"is_frozen":true,"is_explosion_proof":true,"use_soft_pinning":true,"health":1000,"is_networked":true}},{"rotation_axis":2,"model":"xm_prop_x17_hatch_lights","target_version":"3.27b2","num_bones":5,"children":{},"parents_initial_handle":246288,"offset":{"z":1.,"x":0.3,"y":-28.999998},"id":1086,"rotation":{"z":0,"x":0,"y":0},"type":"OBJECT","name":"xm_prop_x17_hatch_lights","world_rotation":{"z":32.411892,"x":-0.062175,"y":-0.018427},"hash":1173877749,"initial_handle":421157,"position":{"z":35.680317,"x":-1378.75232,"y":-2895.36841},"options":{"has_gravity":true,"is_melee_proof":true,"alpha":255,"is_visible":true,"max_health":1000,"is_light_on":true,"is_on_fire":false,"lod_distance":16960,"has_collision":true,"is_attached":true,"bone_index":0,"is_mission_entity":true,"is_bullet_proof":false,"is_dynamic":false,"is_invincible":true,"is_fire_proof":true,"is_frozen":true,"is_explosion_proof":true,"use_soft_pinning":true,"health":1000,"is_networked":true}},{"rotation_axis":2,"model":"xm_base_cia_servertall_01","target_version":"3.27b2","num_bones":0,"children":{},"parents_initial_handle":246288,"offset":{"z":0,"x":-14.900017,"y":-28.400022},"id":1087,"rotation":{"z":-179.999985,"x":90,"y":0.000003},"type":"OBJECT","name":"xm_base_cia_servertall_01","world_rotation":{"z":0,"x":89.937439,"y":-147.588089},"hash":1485713126,"initial_handle":525358,"position":{"z":34.674778,"x":-1391.90515,"y":-2903.00977},"options":{"has_gravity":true,"is_melee_proof":true,"alpha":255,"is_visible":true,"max_health":1000,"is_light_on":true,"is_on_fire":false,"lod_distance":16960,"has_collision":true,"is_attached":true,"bone_index":0,"is_mission_entity":true,"is_bullet_proof":false,"is_dynamic":false,"is_invincible":true,"is_fire_proof":false,"is_frozen":true,"is_explosion_proof":true,"use_soft_pinning":true,"health":1000,"is_networked":true}},{"rotation_axis":2,"model":"xm_base_cia_servertall_01","target_version":"3.27b2","num_bones":0,"children":{},"parents_initial_handle":246288,"offset":{"z":0.06,"x":-15.000001,"y":-28.299997},"id":1088,"rotation":{"z":-179.999985,"x":-90,"y":0},"type":"OBJECT","name":"xm_base_cia_servertall_01","world_rotation":{"z":0,"x":-89.937439,"y":147.588089},"hash":1485713126,"initial_handle":579630,"position":{"z":34.734638,"x":-1392.04333,"y":-2902.979},"options":{"has_gravity":true,"is_melee_proof":true,"alpha":255,"is_visible":true,"max_health":1000,"is_light_on":true,"is_on_fire":false,"lod_distance":16960,"has_collision":true,"is_attached":true,"bone_index":0,"is_mission_entity":true,"is_bullet_proof":false,"is_dynamic":false,"is_invincible":true,"is_fire_proof":false,"is_frozen":true,"is_explosion_proof":true,"use_soft_pinning":true,"health":1000,"is_networked":true}},{"rotation_axis":2,"model":"xm_base_cia_servertall_01","target_version":"3.27b2","num_bones":0,"children":{},"parents_initial_handle":246288,"offset":{"z":0,"x":14.900002,"y":-28.4},"id":1089,"rotation":{"z":0,"x":-90,"y":0},"type":"OBJECT","name":"xm_base_cia_servertall_01","world_rotation":{"z":0,"x":-89.940651,"y":-32.411884},"hash":1485713126,"initial_handle":770606,"position":{"z":34.68436,"x":-1366.74756,"y":-2887.03687},"options":{"has_gravity":true,"is_melee_proof":true,"alpha":255,"is_visible":true,"max_health":1000,"is_light_on":true,"is_on_fire":false,"lod_distance":16960,"has_collision":true,"is_attached":true,"bone_index":0,"is_mission_entity":true,"is_bullet_proof":false,"is_dynamic":false,"is_invincible":true,"is_fire_proof":false,"is_frozen":true,"is_explosion_proof":true,"use_soft_pinning":true,"health":1000,"is_networked":true}},{"rotation_axis":2,"model":"xm_base_cia_servertall_01","target_version":"3.27b2","num_bones":0,"children":{},"parents_initial_handle":246288,"offset":{"z":-0.08,"x":14.999999,"y":-28.399984},"id":1090,"rotation":{"z":0,"x":89.999992,"y":0},"type":"OBJECT","name":"xm_base_cia_servertall_01","world_rotation":{"z":0,"x":89.940651,"y":32.411884},"hash":1485713126,"initial_handle":151343,"position":{"z":34.604393,"x":-1366.66309,"y":-2886.9834},"options":{"has_gravity":true,"is_melee_proof":true,"alpha":255,"is_visible":true,"max_health":1000,"is_light_on":true,"is_on_fire":false,"lod_distance":16960,"has_collision":true,"is_attached":true,"bone_index":0,"is_mission_entity":true,"is_bullet_proof":false,"is_dynamic":false,"is_invincible":true,"is_fire_proof":false,"is_frozen":true,"is_explosion_proof":true,"use_soft_pinning":true,"health":1000,"is_networked":true}},{"rotation_axis":2,"model":"xs_propintarena_lamps_01c","target_version":"3.27b2","num_bones":0,"children":{},"parents_initial_handle":246288,"offset":{"z":-1.8,"x":-5.299997,"y":-2.799999},"id":1091,"rotation":{"z":-89.999992,"x":0,"y":0},"type":"OBJECT","name":"xs_propintarena_lamps_01c","world_rotation":{"z":-57.588062,"x":0.018427,"y":-0.062175},"hash":160683744,"initial_handle":181827,"position":{"z":32.850086,"x":-1397.52087,"y":-2876.25366},"options":{"has_gravity":true,"is_melee_proof":true,"alpha":255,"is_visible":true,"max_health":1000,"is_light_on":true,"is_on_fire":false,"lod_distance":16960,"has_collision":true,"is_attached":true,"bone_index":0,"is_mission_entity":true,"is_bullet_proof":false,"is_dynamic":false,"is_invincible":true,"is_fire_proof":true,"is_frozen":true,"is_explosion_proof":true,"use_soft_pinning":true,"health":1000,"is_networked":true}},{"rotation_axis":2,"model":"xs_propintarena_lamps_01c","target_version":"3.27b2","num_bones":0,"children":{},"parents_initial_handle":246288,"offset":{"z":-1.8,"x":5.299999,"y":-2.799999},"id":1092,"rotation":{"z":89.999992,"x":0,"y":0},"type":"OBJECT","name":"xs_propintarena_lamps_01c","world_rotation":{"z":122.411903,"x":-0.018427,"y":0.062175},"hash":160683744,"initial_handle":276803,"position":{"z":32.853493,"x":-1388.57214,"y":-2870.57202},"options":{"has_gravity":true,"is_melee_proof":true,"alpha":255,"is_visible":true,"max_health":1000,"is_light_on":true,"is_on_fire":false,"lod_distance":16960,"has_collision":true,"is_attached":true,"bone_index":0,"is_mission_entity":true,"is_bullet_proof":false,"is_dynamic":false,"is_invincible":true,"is_fire_proof":true,"is_frozen":true,"is_explosion_proof":true,"use_soft_pinning":true,"health":1000,"is_networked":true}}],"blip_color":2,"blip_handle":82576181,"offset":{"z":0,"x":0,"y":0},"rotation":{"z":0,"x":0,"y":0},"name":"BIGHEAD StarShip","blip_icon":1,"options":{"has_gravity":true,"is_melee_proof":true,"alpha":0,"is_visible":true,"max_health":1000,"is_light_on":true,"lod_distance":16960,"is_networked":true,"has_collision":true,"bone_index":0,"is_mission_entity":true,"health":1000,"is_attached":false,"is_invincible":true,"is_fire_proof":false,"use_soft_pinning":true,"is_explosion_proof":true,"is_dynamic":true,"is_bullet_proof":false,"is_on_fire":false},"created":"2022-11-09T09:11:03Z","author":"unknown","vehicle_attributes":{"wheels":{"tire_smoke_color":{"r":255,"g":255,"b":255},"bulletproof_tires":false,"wheel_type":0,"invisible_wheels":false,"tires_burst":{}},"windows":{"rolled_down":{},"broken":{"frontleft":false,"rearright":false,"frontright":false,"rearleft":false,"front":false,"rear":false}},"mods":{"_40":-1,"_24":-1,"_48":-1,"_13":-1,"_28":-1,"_49":-1,"_25":-1,"_29":-1,"_42":-1,"_46":-1,"_26":-1,"_21":false,"_41":-1,"_3":-1,"_7":-1,"_1":-1,"_22":false,"_45":-1,"_27":-1,"_12":-1,"_37":-1,"_44":-1,"_9":-1,"_14":-1,"_34":-1,"_5":-1,"_47":-1,"_38":-1,"_43":-1,"_30":-1,"_15":-1,"_10":-1,"_33":-1,"_39":-1,"_20":false,"_8":-1,"_11":-1,"_23":-1,"_36":-1,"_18":false,"_31":-1,"_16":-1,"_2":-1,"_4":-1,"_0":-1,"_6":-1,"_19":false,"_32":-1,"_17":false,"_35":-1},"doors":{"open":{"backright":false,"frontleft":false,"hood":false,"frontright":false,"backleft":false,"trunk":false,"trunk2":false},"broken":{"backright":false,"frontleft":false,"hood":false,"frontright":false,"backleft":false,"trunk":false,"trunk2":false}},"paint":{"dashboard_color":0,"interior_color":0,"primary":{"color":-1,"is_custom":false,"custom_color":{},"pearlescent_color":-1,"vehicle_standard_color":121,"paint_type":6},"livery":-1,"dirt_level":0.000001,"livery_legacy":-1,"livery2_legacy":-1,"extra_colors":{"pearlescent":8,"wheel":156},"fade":0.298039,"vehicle_custom_color":{"r":176,"g":176,"b":176},"color_combo":0,"secondary":{"color":-1,"is_custom":false,"custom_color":{},"vehicle_standard_color":121,"paint_type":6}},"neon":{"color":{"r":255,"g":0,"b":255},"lights":{"left":false,"front":false,"back":false,"right":false}},"extras":{"_5":false,"_14":false,"_3":false,"_11":false,"_9":false,"_13":false,"_0":false,"_2":true,"_4":false,"_7":false,"_6":false,"_1":true,"_10":false,"_8":false,"_12":false},"headlights":{"headlights_color":255,"headlights_type":false},"options":{"emergency_lights":false,"siren":false,"license_plate_text":"23VWC901","search_light":false,"radio_loud":false,"license_plate_type":0,"window_tint":-1,"bulletproof_tires":true,"engine_running":true}},"position":{"z":11.685701,"x":-1602.28417,"y":-2870.399859},"version":"Constructor 0.27b4 / 3.27b2 / 0.8.5b8","model":"hydra","num_bones":52,"type":"VEHICLE","blip_sprite":1,"world_rotation":{"z":0,"x":0,"y":0},"hash":970385471,"initial_handle":246288,"id":1071,"rotation_axis":2}